<?xml version="1.0" encoding="UTF-8"?><ns2:order xmlns:ns2="http://oxseed.com/data/order" xmlns:ns3="http://oxseed.com/data/commons/entrylist" xmlns:ns4="http://oxseed.com/data/extension/metadata" xmlns:ns5="http://oxseed.com/data/extension/orderdeps"><id>201104152251269991012FDDCFACD6481FCEBC7A7B416A92296D100000000b74286a270</id><stack><id>GP-Frachtbr_intern_20110415103754675.split_fileImport_working_20110415225109_1680892454_pod</id><processList><process><id>201104152251281060a280a5667c67689a6</id><documentList><document><id></id><idType/><actionList/><inputType/><documentType>import_protocol</documentType><indexData><indexFieldList><indexField><name>document_id_str</name><value>201104152251277300008489C19C93A7EC4F1176C04BD6607A1C4000000008ee1e7b524</value></indexField><indexField><name>document_type_str</name><value>Ablieferbeleg</value></indexField><indexField><name>dokumentennummer_str</name><value>11162882</value></indexField><indexField><name>export_boolean</name><value>false</value></indexField><indexField><name>input_file_name_str</name><value>/mnt/work/servicemix/working_directory/import/imported/wackler/GP-Frachtbr_intern_20110415103754675.split_fileImport_working_20110415225109_1680892454_pod_201104152251290620966/201104152251277300008489C19C93A7EC4F1176C04BD6607A1C4000000008ee1e7b524_37380997</value></indexField><indexField><name>page_count_int</name><value>4</value></indexField><indexField><name>recovery_id_ftxt</name><value> OXSEED-8071 OXSEED-8071J</value></indexField><indexField><name>recovery_id_str</name><value>OXSEED-8071A2</value></indexField><indexField><name>toverify_boolean</name><value>false</value></indexField><indexField><name>update_boolean</name><value>false</value></indexField></indexFieldList></indexData><additionalDocumentInfo/></document></documentList><actionList/><processType>administration</processType><processPriority/><indexData><indexFieldList><indexField><name>pi_eingangsdatum_date</name><value>2011-04-15T22:51:28.109Z</value></indexField><indexField><name>pi_full_path</name><value>/Akte-Spedition/POD/Ablieferbeleg/2011/</value></indexField><indexField><name>pi_import_path_str</name><value>/mnt/shared/wackler/import@wackler.oxseed.net/data/pod/ablieferbeleg/intern/201104152130/GP-Frachtbr_intern_20110415103754675.split</value></indexField><indexField><name>pi_inputchannel_str</name><value>import_pod</value></indexField><indexField><name>pi_level_0</name><value>Akte-Spedition</value></indexField><indexField><name>pi_level_1</name><value>POD</value></indexField><indexField><name>pi_level_2</name><value>Ablieferbeleg</value></indexField><indexField><name>pi_level_3</name><value>2011</value></indexField><indexField><name>pi_mandant_str</name><value>wackler</value></indexField><indexField><name>pi_order_id_str</name><value>201104152251269991012FDDCFACD6481FCEBC7A7B416A92296D100000000b74286a270</value></indexField><indexField><name>pi_process_id_str</name><value>201104152251281060a280a5667c67689a6</value></indexField><indexField><name>pi_process_type_str</name><value>POD</value></indexField><indexField><name>pi_sm_status_str</name><value>finished</value></indexField><indexField><name>pi_stack_id_str</name><value>GP-Frachtbr_intern_20110415103754675.split_fileImport_working_20110415225109_1680892454_pod</value></indexField></indexFieldList></indexData><additionalProcessInfo/><systemMessages/></process><process><id>201104152251280890a280a566a91bcaa01</id><documentList><document><id></id><idType/><actionList/><inputType/><documentType>import_protocol</documentType><indexData><indexFieldList><indexField><name>document_id_str</name><value>201104152251272840008D22044D6DC5F01EB315685C07EDAF5AA00000000144b84fe05</value></indexField><indexField><name>document_type_str</name><value>Ablieferbeleg</value></indexField><indexField><name>dokumentennummer_str</name><value>11162878</value></indexField><indexField><name>export_boolean</name><value>false</value></indexField><indexField><name>input_file_name_str</name><value>/mnt/work/servicemix/working_directory/import/imported/wackler/GP-Frachtbr_intern_20110415103754675.split_fileImport_working_20110415225109_1680892454_pod_201104152251290620966/201104152251272840008D22044D6DC5F01EB315685C07EDAF5AA00000000144b84fe05_17077186</value></indexField><indexField><name>page_count_int</name><value>3</value></indexField><indexField><name>recovery_id_ftxt</name><value> OXSEED-8071 OXSEED-8071J</value></indexField><indexField><name>recovery_id_str</name><value>OXSEED-8071A2</value></indexField><indexField><name>toverify_boolean</name><value>false</value></indexField><indexField><name>update_boolean</name><value>false</value></indexField></indexFieldList></indexData><additionalDocumentInfo/></document></documentList><actionList/><processType>administration</processType><processPriority/><indexData><indexFieldList><indexField><name>pi_eingangsdatum_date</name><value>2011-04-15T22:51:28.092Z</value></indexField><indexField><name>pi_full_path</name><value>/Akte-Spedition/POD/Ablieferbeleg/2011/</value></indexField><indexField><name>pi_import_path_str</name><value>/mnt/shared/wackler/import@wackler.oxseed.net/data/pod/ablieferbeleg/intern/201104152130/GP-Frachtbr_intern_20110415103754675.split</value></indexField><indexField><name>pi_inputchannel_str</name><value>import_pod</value></indexField><indexField><name>pi_level_0</name><value>Akte-Spedition</value></indexField><indexField><name>pi_level_1</name><value>POD</value></indexField><indexField><name>pi_level_2</name><value>Ablieferbeleg</value></indexField><indexField><name>pi_level_3</name><value>2011</value></indexField><indexField><name>pi_mandant_str</name><value>wackler</value></indexField><indexField><name>pi_order_id_str</name><value>201104152251269991012FDDCFACD6481FCEBC7A7B416A92296D100000000b74286a270</value></indexField><indexField><name>pi_process_id_str</name><value>201104152251280890a280a566a91bcaa01</value></indexField><indexField><name>pi_process_type_str</name><value>POD</value></indexField><indexField><name>pi_sm_status_str</name><value>finished</value></indexField><indexField><name>pi_stack_id_str</name><value>GP-Frachtbr_intern_20110415103754675.split_fileImport_working_20110415225109_1680892454_pod</value></indexField></indexFieldList></indexData><additionalProcessInfo/><systemMessages/></process><process><id>201104152251280960a280a5644ab11b5f4</id><documentList><document><id></id><idType/><actionList/><inputType/><documentType>import_protocol</documentType><indexData><indexFieldList><indexField><name>document_id_str</name><value>2011041522512746100089299DDE2A183A6A81F177538EE2F2B7D00000000e87ac60d05</value></indexField><indexField><name>document_type_str</name><value>Ablieferbeleg</value></indexField><indexField><name>dokumentennummer_str</name><value>11162917</value></indexField><indexField><name>export_boolean</name><value>false</value></indexField><indexField><name>input_file_name_str</name><value>/mnt/work/servicemix/working_directory/import/imported/wackler/GP-Frachtbr_intern_20110415103754675.split_fileImport_working_20110415225109_1680892454_pod_201104152251290620966/2011041522512746100089299DDE2A183A6A81F177538EE2F2B7D00000000e87ac60d05_07605805</value></indexField><indexField><name>page_count_int</name><value>3</value></indexField><indexField><name>recovery_id_ftxt</name><value> OXSEED-8071 OXSEED-8071J</value></indexField><indexField><name>recovery_id_str</name><value>OXSEED-8071A2</value></indexField><indexField><name>toverify_boolean</name><value>false</value></indexField><indexField><name>update_boolean</name><value>false</value></indexField></indexFieldList></indexData><additionalDocumentInfo/></document></documentList><actionList/><processType>administration</processType><processPriority/><indexData><indexFieldList><indexField><name>pi_eingangsdatum_date</name><value>2011-04-15T22:51:28.099Z</value></indexField><indexField><name>pi_full_path</name><value>/Akte-Spedition/POD/Ablieferbeleg/2011/</value></indexField><indexField><name>pi_import_path_str</name><value>/mnt/shared/wackler/import@wackler.oxseed.net/data/pod/ablieferbeleg/intern/201104152130/GP-Frachtbr_intern_20110415103754675.split</value></indexField><indexField><name>pi_inputchannel_str</name><value>import_pod</value></indexField><indexField><name>pi_level_0</name><value>Akte-Spedition</value></indexField><indexField><name>pi_level_1</name><value>POD</value></indexField><indexField><name>pi_level_2</name><value>Ablieferbeleg</value></indexField><indexField><name>pi_level_3</name><value>2011</value></indexField><indexField><name>pi_mandant_str</name><value>wackler</value></indexField><indexField><name>pi_order_id_str</name><value>201104152251269991012FDDCFACD6481FCEBC7A7B416A92296D100000000b74286a270</value></indexField><indexField><name>pi_process_id_str</name><value>201104152251280960a280a5644ab11b5f4</value></indexField><indexField><name>pi_process_type_str</name><value>POD</value></indexField><indexField><name>pi_sm_status_str</name><value>finished</value></indexField><indexField><name>pi_stack_id_str</name><value>GP-Frachtbr_intern_20110415103754675.split_fileImport_working_20110415225109_1680892454_pod</value></indexField></indexFieldList></indexData><additionalProcessInfo/><systemMessages/></process><process><id>201104152251280830a280a56b7a82c3c89</id><documentList><document><id></id><idType/><actionList/><inputType/><documentType>import_protocol</documentType><indexData><indexFieldList><indexField><name>document_id_str</name><value>2011041522512708500081045619409B7A7941C93AEFCD54C80E9000000008845b52f14</value></indexField><indexField><name>document_type_str</name><value>Ablieferbeleg</value></indexField><indexField><name>dokumentennummer_str</name><value>11161709</value></indexField><indexField><name>export_boolean</name><value>false</value></indexField><indexField><name>input_file_name_str</name><value>/mnt/work/servicemix/working_directory/import/imported/wackler/GP-Frachtbr_intern_20110415103754675.split_fileImport_working_20110415225109_1680892454_pod_201104152251290620966/2011041522512708500081045619409B7A7941C93AEFCD54C80E9000000008845b52f14_17039877</value></indexField><indexField><name>page_count_int</name><value>4</value></indexField><indexField><name>recovery_id_ftxt</name><value> OXSEED-8071 OXSEED-8071J</value></indexField><indexField><name>recovery_id_str</name><value>OXSEED-8071A2</value></indexField><indexField><name>toverify_boolean</name><value>false</value></indexField><indexField><name>update_boolean</name><value>false</value></indexField></indexFieldList></indexData><additionalDocumentInfo/></document></documentList><actionList/><processType>administration</processType><processPriority/><indexData><indexFieldList><indexField><name>pi_eingangsdatum_date</name><value>2011-04-15T22:51:28.086Z</value></indexField><indexField><name>pi_full_path</name><value>/Akte-Spedition/POD/Ablieferbeleg/2011/</value></indexField><indexField><name>pi_import_path_str</name><value>/mnt/shared/wackler/import@wackler.oxseed.net/data/pod/ablieferbeleg/intern/201104152130/GP-Frachtbr_intern_20110415103754675.split</value></indexField><indexField><name>pi_inputchannel_str</name><value>import_pod</value></indexField><indexField><name>pi_level_0</name><value>Akte-Spedition</value></indexField><indexField><name>pi_level_1</name><value>POD</value></indexField><indexField><name>pi_level_2</name><value>Ablieferbeleg</value></indexField><indexField><name>pi_level_3</name><value>2011</value></indexField><indexField><name>pi_mandant_str</name><value>wackler</value></indexField><indexField><name>pi_order_id_str</name><value>201104152251269991012FDDCFACD6481FCEBC7A7B416A92296D100000000b74286a270</value></indexField><indexField><name>pi_process_id_str</name><value>201104152251280830a280a56b7a82c3c89</value></indexField><indexField><name>pi_process_type_str</name><value>POD</value></indexField><indexField><name>pi_sm_status_str</name><value>finished</value></indexField><indexField><name>pi_stack_id_str</name><value>GP-Frachtbr_intern_20110415103754675.split_fileImport_working_20110415225109_1680892454_pod</value></indexField></indexFieldList></indexData><additionalProcessInfo/><systemMessages/></process><process><id>201104152251280930a280a5691a2f4b997</id><documentList><document><id></id><idType/><actionList/><inputType/><documentType>import_protocol</documentType><indexData><indexFieldList><indexField><name>document_id_str</name><value>201104152251273690008680D41ADEEDCA99EE1651BEDAECE7DB700000000ed9a33784f</value></indexField><indexField><name>document_type_str</name><value>Ablieferbeleg</value></indexField><indexField><name>dokumentennummer_str</name><value>11161708</value></indexField><indexField><name>export_boolean</name><value>false</value></indexField><indexField><name>input_file_name_str</name><value>/mnt/work/servicemix/working_directory/import/imported/wackler/GP-Frachtbr_intern_20110415103754675.split_fileImport_working_20110415225109_1680892454_pod_201104152251290620966/201104152251273690008680D41ADEEDCA99EE1651BEDAECE7DB700000000ed9a33784f_12224897</value></indexField><indexField><name>page_count_int</name><value>2</value></indexField><indexField><name>recovery_id_ftxt</name><value> OXSEED-8071 OXSEED-8071J</value></indexField><indexField><name>recovery_id_str</name><value>OXSEED-8071A2</value></indexField><indexField><name>toverify_boolean</name><value>false</value></indexField><indexField><name>update_boolean</name><value>false</value></indexField></indexFieldList></indexData><additionalDocumentInfo/></document></documentList><actionList/><processType>administration</processType><processPriority/><indexData><indexFieldList><indexField><name>pi_eingangsdatum_date</name><value>2011-04-15T22:51:28.096Z</value></indexField><indexField><name>pi_full_path</name><value>/Akte-Spedition/POD/Ablieferbeleg/2011/</value></indexField><indexField><name>pi_import_path_str</name><value>/mnt/shared/wackler/import@wackler.oxseed.net/data/pod/ablieferbeleg/intern/201104152130/GP-Frachtbr_intern_20110415103754675.split</value></indexField><indexField><name>pi_inputchannel_str</name><value>import_pod</value></indexField><indexField><name>pi_level_0</name><value>Akte-Spedition</value></indexField><indexField><name>pi_level_1</name><value>POD</value></indexField><indexField><name>pi_level_2</name><value>Ablieferbeleg</value></indexField><indexField><name>pi_level_3</name><value>2011</value></indexField><indexField><name>pi_mandant_str</name><value>wackler</value></indexField><indexField><name>pi_order_id_str</name><value>201104152251269991012FDDCFACD6481FCEBC7A7B416A92296D100000000b74286a270</value></indexField><indexField><name>pi_process_id_str</name><value>201104152251280930a280a5691a2f4b997</value></indexField><indexField><name>pi_process_type_str</name><value>POD</value></indexField><indexField><name>pi_sm_status_str</name><value>finished</value></indexField><indexField><name>pi_stack_id_str</name><value>GP-Frachtbr_intern_20110415103754675.split_fileImport_working_20110415225109_1680892454_pod</value></indexField></indexFieldList></indexData><additionalProcessInfo/><systemMessages/></process><process><id>201104152251280990a280a5651a5c35523</id><documentList><document><id></id><idType/><actionList/><inputType/><documentType>import_protocol</documentType><indexData><indexFieldList><indexField><name>document_id_str</name><value>201104152251275490008286A0214D0F9F66239A689F819F07C5200000000380b13fc49</value></indexField><indexField><name>document_type_str</name><value>Ablieferbeleg</value></indexField><indexField><name>dokumentennummer_str</name><value>11161669</value></indexField><indexField><name>export_boolean</name><value>false</value></indexField><indexField><name>input_file_name_str</name><value>/mnt/work/servicemix/working_directory/import/imported/wackler/GP-Frachtbr_intern_20110415103754675.split_fileImport_working_20110415225109_1680892454_pod_201104152251290620966/201104152251275490008286A0214D0F9F66239A689F819F07C5200000000380b13fc49_10405455</value></indexField><indexField><name>page_count_int</name><value>2</value></indexField><indexField><name>recovery_id_ftxt</name><value> OXSEED-8071 OXSEED-8071J</value></indexField><indexField><name>recovery_id_str</name><value>OXSEED-8071A2</value></indexField><indexField><name>toverify_boolean</name><value>false</value></indexField><indexField><name>update_boolean</name><value>false</value></indexField></indexFieldList></indexData><additionalDocumentInfo/></document></documentList><actionList/><processType>administration</processType><processPriority/><indexData><indexFieldList><indexField><name>pi_eingangsdatum_date</name><value>2011-04-15T22:51:28.102Z</value></indexField><indexField><name>pi_full_path</name><value>/Akte-Spedition/POD/Ablieferbeleg/2011/</value></indexField><indexField><name>pi_import_path_str</name><value>/mnt/shared/wackler/import@wackler.oxseed.net/data/pod/ablieferbeleg/intern/201104152130/GP-Frachtbr_intern_20110415103754675.split</value></indexField><indexField><name>pi_inputchannel_str</name><value>import_pod</value></indexField><indexField><name>pi_level_0</name><value>Akte-Spedition</value></indexField><indexField><name>pi_level_1</name><value>POD</value></indexField><indexField><name>pi_level_2</name><value>Ablieferbeleg</value></indexField><indexField><name>pi_level_3</name><value>2011</value></indexField><indexField><name>pi_mandant_str</name><value>wackler</value></indexField><indexField><name>pi_order_id_str</name><value>201104152251269991012FDDCFACD6481FCEBC7A7B416A92296D100000000b74286a270</value></indexField><indexField><name>pi_process_id_str</name><value>201104152251280990a280a5651a5c35523</value></indexField><indexField><name>pi_process_type_str</name><value>POD</value></indexField><indexField><name>pi_sm_status_str</name><value>finished</value></indexField><indexField><name>pi_stack_id_str</name><value>GP-Frachtbr_intern_20110415103754675.split_fileImport_working_20110415225109_1680892454_pod</value></indexField></indexFieldList></indexData><additionalProcessInfo/><systemMessages/></process><process><id>201104152251281150a280a564a753aa0b7</id><documentList><document><id></id><idType/><actionList/><inputType/><documentType>import_protocol</documentType><indexData><indexFieldList><indexField><name>document_id_str</name><value>2011041522512799300082AD56BDC94C413FC6EDD86B589198DC2000000000ef05e1919</value></indexField><indexField><name>document_type_str</name><value>Ablieferbeleg</value></indexField><indexField><name>dokumentennummer_str</name><value>11162880</value></indexField><indexField><name>export_boolean</name><value>false</value></indexField><indexField><name>input_file_name_str</name><value>/mnt/work/servicemix/working_directory/import/imported/wackler/GP-Frachtbr_intern_20110415103754675.split_fileImport_working_20110415225109_1680892454_pod_201104152251290620966/2011041522512799300082AD56BDC94C413FC6EDD86B589198DC2000000000ef05e1919_73579567</value></indexField><indexField><name>page_count_int</name><value>3</value></indexField><indexField><name>recovery_id_ftxt</name><value> OXSEED-8071 OXSEED-8071J</value></indexField><indexField><name>recovery_id_str</name><value>OXSEED-8071A2</value></indexField><indexField><name>toverify_boolean</name><value>false</value></indexField><indexField><name>update_boolean</name><value>false</value></indexField></indexFieldList></indexData><additionalDocumentInfo/></document></documentList><actionList/><processType>administration</processType><processPriority/><indexData><indexFieldList><indexField><name>pi_eingangsdatum_date</name><value>2011-04-15T22:51:28.118Z</value></indexField><indexField><name>pi_full_path</name><value>/Akte-Spedition/POD/Ablieferbeleg/2011/</value></indexField><indexField><name>pi_import_path_str</name><value>/mnt/shared/wackler/import@wackler.oxseed.net/data/pod/ablieferbeleg/intern/201104152130/GP-Frachtbr_intern_20110415103754675.split</value></indexField><indexField><name>pi_inputchannel_str</name><value>import_pod</value></indexField><indexField><name>pi_level_0</name><value>Akte-Spedition</value></indexField><indexField><name>pi_level_1</name><value>POD</value></indexField><indexField><name>pi_level_2</name><value>Ablieferbeleg</value></indexField><indexField><name>pi_level_3</name><value>2011</value></indexField><indexField><name>pi_mandant_str</name><value>wackler</value></indexField><indexField><name>pi_order_id_str</name><value>201104152251269991012FDDCFACD6481FCEBC7A7B416A92296D100000000b74286a270</value></indexField><indexField><name>pi_process_id_str</name><value>201104152251281150a280a564a753aa0b7</value></indexField><indexField><name>pi_process_type_str</name><value>POD</value></indexField><indexField><name>pi_sm_status_str</name><value>finished</value></indexField><indexField><name>pi_stack_id_str</name><value>GP-Frachtbr_intern_20110415103754675.split_fileImport_working_20110415225109_1680892454_pod</value></indexField></indexFieldList></indexData><additionalProcessInfo/><systemMessages/></process><process><id>201104152251281180a280a56a5271370dc</id><documentList><document><id></id><idType/><actionList/><inputType/><documentType>import_protocol</documentType><indexData><indexFieldList><indexField><name>document_id_str</name><value>2011041522512808100087E4DF2E2B144E7BEA5A5B8D30E5A3E9A00000000f0f765ce70</value></indexField><indexField><name>document_type_str</name><value>Ablieferbeleg</value></indexField><indexField><name>dokumentennummer_str</name><value>11161666</value></indexField><indexField><name>export_boolean</name><value>false</value></indexField><indexField><name>input_file_name_str</name><value>/mnt/work/servicemix/working_directory/import/imported/wackler/GP-Frachtbr_intern_20110415103754675.split_fileImport_working_20110415225109_1680892454_pod_201104152251290620966/2011041522512808100087E4DF2E2B144E7BEA5A5B8D30E5A3E9A00000000f0f765ce70_19530891</value></indexField><indexField><name>page_count_int</name><value>2</value></indexField><indexField><name>recovery_id_ftxt</name><value> OXSEED-8071 OXSEED-8071J</value></indexField><indexField><name>recovery_id_str</name><value>OXSEED-8071A2</value></indexField><indexField><name>toverify_boolean</name><value>false</value></indexField><indexField><name>update_boolean</name><value>false</value></indexField></indexFieldList></indexData><additionalDocumentInfo/></document></documentList><actionList/><processType>administration</processType><processPriority/><indexData><indexFieldList><indexField><name>pi_eingangsdatum_date</name><value>2011-04-15T22:51:28.121Z</value></indexField><indexField><name>pi_full_path</name><value>/Akte-Spedition/POD/Ablieferbeleg/2011/</value></indexField><indexField><name>pi_import_path_str</name><value>/mnt/shared/wackler/import@wackler.oxseed.net/data/pod/ablieferbeleg/intern/201104152130/GP-Frachtbr_intern_20110415103754675.split</value></indexField><indexField><name>pi_inputchannel_str</name><value>import_pod</value></indexField><indexField><name>pi_level_0</name><value>Akte-Spedition</value></indexField><indexField><name>pi_level_1</name><value>POD</value></indexField><indexField><name>pi_level_2</name><value>Ablieferbeleg</value></indexField><indexField><name>pi_level_3</name><value>2011</value></indexField><indexField><name>pi_mandant_str</name><value>wackler</value></indexField><indexField><name>pi_order_id_str</name><value>201104152251269991012FDDCFACD6481FCEBC7A7B416A92296D100000000b74286a270</value></indexField><indexField><name>pi_process_id_str</name><value>201104152251281180a280a56a5271370dc</value></indexField><indexField><name>pi_process_type_str</name><value>POD</value></indexField><indexField><name>pi_sm_status_str</name><value>finished</value></indexField><indexField><name>pi_stack_id_str</name><value>GP-Frachtbr_intern_20110415103754675.split_fileImport_working_20110415225109_1680892454_pod</value></indexField></indexFieldList></indexData><additionalProcessInfo/><systemMessages/></process></processList><additionalStackInfo/></stack><actionList/><mandant>wackler</mandant><inputChannel/><exportChannel/><additionalOrderInfo/></ns2:order>