<?xml version="1.0" encoding="UTF-8"?><ns2:order xmlns:ns2="http://oxseed.com/data/order" xmlns:ns3="http://oxseed.com/data/commons/entrylist" xmlns:ns4="http://oxseed.com/data/extension/metadata" xmlns:ns5="http://oxseed.com/data/extension/orderdeps"><id>201104152229261441012FD2155D8F525BA0577DDDF0A2D36E1B4000000000642cda0e5</id><stack><id>DD-Frachtbr_extern_20110415202651942.split_fileImport_working_20110415222858_1313201843_pod</id><processList><process><id>201104152229282510a280a5646518f6352</id><documentList><document><id>201104152229272610008807361E638E60D9C875F9E9B1FC7CFA900000000b4b4014414</id><idType/><actionList/><inputType/><documentType>import_protocol</documentType><indexData><indexFieldList><indexField><name>depot_number_str</name><value>4017</value></indexField><indexField><name>document_id_str</name><value>201104152229272610008807361E638E60D9C875F9E9B1FC7CFA900000000b4b4014414</value></indexField><indexField><name>document_type_str</name><value>Ablieferbeleg</value></indexField><indexField><name>dokumentennummer_str</name><value>41123183</value></indexField><indexField><name>export_boolean</name><value>true</value></indexField><indexField><name>input_file_name_str</name><value>/mnt/work/servicemix/working_directory/import/imported/wackler/DD-Frachtbr_extern_20110415202651942.split_fileImport_working_20110415222858_1313201843_pod_201104152229292085934/201104152229272610008807361E638E60D9C875F9E9B1FC7CFA900000000b4b4014414_20352906</value></indexField><indexField><name>page_count_int</name><value>2</value></indexField><indexField><name>recovery_id_ftxt</name><value> OXSEED-8071 OXSEED-8071J</value></indexField><indexField><name>recovery_id_str</name><value>OXSEED-8071A2</value></indexField><indexField><name>toverify_boolean</name><value>false</value></indexField><indexField><name>update_boolean</name><value>false</value></indexField></indexFieldList></indexData><additionalDocumentInfo/></document></documentList><actionList/><processType>administration</processType><processPriority/><indexData><indexFieldList><indexField><name>pi_eingangsdatum_date</name><value>2011-04-15T22:29:28.255Z</value></indexField><indexField><name>pi_full_path</name><value>/Akte-Spedition/POD/Ablieferbeleg/2011/</value></indexField><indexField><name>pi_import_path_str</name><value>/mnt/shared/wackler/import@wackler.oxseed.net/data/pod/ablieferbeleg/extern/4017/201104152130/DD-Frachtbr_extern_20110415202651942.split</value></indexField><indexField><name>pi_inputchannel_str</name><value>import_pod_extern</value></indexField><indexField><name>pi_level_0</name><value>Akte-Spedition</value></indexField><indexField><name>pi_level_1</name><value>POD</value></indexField><indexField><name>pi_level_2</name><value>Ablieferbeleg</value></indexField><indexField><name>pi_level_3</name><value>2011</value></indexField><indexField><name>pi_mandant_str</name><value>wackler</value></indexField><indexField><name>pi_order_id_str</name><value>201104152229261441012FD2155D8F525BA0577DDDF0A2D36E1B4000000000642cda0e5</value></indexField><indexField><name>pi_process_id_str</name><value>201104152229282510a280a5646518f6352</value></indexField><indexField><name>pi_process_type_str</name><value>POD</value></indexField><indexField><name>pi_sm_status_str</name><value>finished</value></indexField><indexField><name>pi_stack_id_str</name><value>DD-Frachtbr_extern_20110415202651942.split_fileImport_working_20110415222858_1313201843_pod</value></indexField></indexFieldList></indexData><additionalProcessInfo/><systemMessages/></process><process><id>201104152229282440a280a56d314f51893</id><documentList><document><id>20110415222927079000822FC4597951CEBDDE06A6D89B6FB8ECB00000000cd68597e88</id><idType/><actionList/><inputType/><documentType>import_protocol</documentType><indexData><indexFieldList><indexField><name>depot_number_str</name><value>4017</value></indexField><indexField><name>document_id_str</name><value>20110415222927079000822FC4597951CEBDDE06A6D89B6FB8ECB00000000cd68597e88</value></indexField><indexField><name>document_type_str</name><value>Ablieferbeleg</value></indexField><indexField><name>dokumentennummer_str</name><value>41121204</value></indexField><indexField><name>export_boolean</name><value>true</value></indexField><indexField><name>input_file_name_str</name><value>/mnt/work/servicemix/working_directory/import/imported/wackler/DD-Frachtbr_extern_20110415202651942.split_fileImport_working_20110415222858_1313201843_pod_201104152229292085934/20110415222927079000822FC4597951CEBDDE06A6D89B6FB8ECB00000000cd68597e88_16432008</value></indexField><indexField><name>page_count_int</name><value>5</value></indexField><indexField><name>recovery_id_ftxt</name><value> OXSEED-8071 OXSEED-8071J</value></indexField><indexField><name>recovery_id_str</name><value>OXSEED-8071A2</value></indexField><indexField><name>toverify_boolean</name><value>false</value></indexField><indexField><name>update_boolean</name><value>false</value></indexField></indexFieldList></indexData><additionalDocumentInfo/></document></documentList><actionList/><processType>administration</processType><processPriority/><indexData><indexFieldList><indexField><name>pi_eingangsdatum_date</name><value>2011-04-15T22:29:28.248Z</value></indexField><indexField><name>pi_full_path</name><value>/Akte-Spedition/POD/Ablieferbeleg/2011/</value></indexField><indexField><name>pi_import_path_str</name><value>/mnt/shared/wackler/import@wackler.oxseed.net/data/pod/ablieferbeleg/extern/4017/201104152130/DD-Frachtbr_extern_20110415202651942.split</value></indexField><indexField><name>pi_inputchannel_str</name><value>import_pod_extern</value></indexField><indexField><name>pi_level_0</name><value>Akte-Spedition</value></indexField><indexField><name>pi_level_1</name><value>POD</value></indexField><indexField><name>pi_level_2</name><value>Ablieferbeleg</value></indexField><indexField><name>pi_level_3</name><value>2011</value></indexField><indexField><name>pi_mandant_str</name><value>wackler</value></indexField><indexField><name>pi_order_id_str</name><value>201104152229261441012FD2155D8F525BA0577DDDF0A2D36E1B4000000000642cda0e5</value></indexField><indexField><name>pi_process_id_str</name><value>201104152229282440a280a56d314f51893</value></indexField><indexField><name>pi_process_type_str</name><value>POD</value></indexField><indexField><name>pi_sm_status_str</name><value>finished</value></indexField><indexField><name>pi_stack_id_str</name><value>DD-Frachtbr_extern_20110415202651942.split_fileImport_working_20110415222858_1313201843_pod</value></indexField></indexFieldList></indexData><additionalProcessInfo/><systemMessages/></process><process><id>201104152229282240a280a5659ddd82add</id><documentList><document><id>20110415222926604000894DA70677AACAE4083518B6A9B0EB6310000000085ee357d49</id><idType/><actionList/><inputType/><documentType>import_protocol</documentType><indexData><indexFieldList><indexField><name>depot_number_str</name><value>4017</value></indexField><indexField><name>document_id_str</name><value>20110415222926604000894DA70677AACAE4083518B6A9B0EB6310000000085ee357d49</value></indexField><indexField><name>document_type_str</name><value>Ablieferbeleg</value></indexField><indexField><name>dokumentennummer_str</name><value>41123557</value></indexField><indexField><name>export_boolean</name><value>true</value></indexField><indexField><name>input_file_name_str</name><value>/mnt/work/servicemix/working_directory/import/imported/wackler/DD-Frachtbr_extern_20110415202651942.split_fileImport_working_20110415222858_1313201843_pod_201104152229292085934/20110415222926604000894DA70677AACAE4083518B6A9B0EB6310000000085ee357d49_80344876</value></indexField><indexField><name>page_count_int</name><value>3</value></indexField><indexField><name>recovery_id_ftxt</name><value> OXSEED-8071 OXSEED-8071J</value></indexField><indexField><name>recovery_id_str</name><value>OXSEED-8071A2</value></indexField><indexField><name>toverify_boolean</name><value>false</value></indexField><indexField><name>update_boolean</name><value>false</value></indexField></indexFieldList></indexData><additionalDocumentInfo/></document></documentList><actionList/><processType>administration</processType><processPriority/><indexData><indexFieldList><indexField><name>pi_eingangsdatum_date</name><value>2011-04-15T22:29:28.228Z</value></indexField><indexField><name>pi_full_path</name><value>/Akte-Spedition/POD/Ablieferbeleg/2011/</value></indexField><indexField><name>pi_import_path_str</name><value>/mnt/shared/wackler/import@wackler.oxseed.net/data/pod/ablieferbeleg/extern/4017/201104152130/DD-Frachtbr_extern_20110415202651942.split</value></indexField><indexField><name>pi_inputchannel_str</name><value>import_pod_extern</value></indexField><indexField><name>pi_level_0</name><value>Akte-Spedition</value></indexField><indexField><name>pi_level_1</name><value>POD</value></indexField><indexField><name>pi_level_2</name><value>Ablieferbeleg</value></indexField><indexField><name>pi_level_3</name><value>2011</value></indexField><indexField><name>pi_mandant_str</name><value>wackler</value></indexField><indexField><name>pi_order_id_str</name><value>201104152229261441012FD2155D8F525BA0577DDDF0A2D36E1B4000000000642cda0e5</value></indexField><indexField><name>pi_process_id_str</name><value>201104152229282240a280a5659ddd82add</value></indexField><indexField><name>pi_process_type_str</name><value>POD</value></indexField><indexField><name>pi_sm_status_str</name><value>finished</value></indexField><indexField><name>pi_stack_id_str</name><value>DD-Frachtbr_extern_20110415202651942.split_fileImport_working_20110415222858_1313201843_pod</value></indexField></indexFieldList></indexData><additionalProcessInfo/><systemMessages/></process><process><id>201104152229282280a280a565622e4204a</id><documentList><document><id>201104152229267000008C126B0D261267124805B53180C66198D000000008f64a32ae6</id><idType/><actionList/><inputType/><documentType>import_protocol</documentType><indexData><indexFieldList><indexField><name>depot_number_str</name><value>4017</value></indexField><indexField><name>document_id_str</name><value>201104152229267000008C126B0D261267124805B53180C66198D000000008f64a32ae6</value></indexField><indexField><name>document_type_str</name><value>Ablieferbeleg</value></indexField><indexField><name>dokumentennummer_str</name><value>41121586</value></indexField><indexField><name>export_boolean</name><value>true</value></indexField><indexField><name>input_file_name_str</name><value>/mnt/work/servicemix/working_directory/import/imported/wackler/DD-Frachtbr_extern_20110415202651942.split_fileImport_working_20110415222858_1313201843_pod_201104152229292085934/201104152229267000008C126B0D261267124805B53180C66198D000000008f64a32ae6_10055262</value></indexField><indexField><name>page_count_int</name><value>4</value></indexField><indexField><name>recovery_id_ftxt</name><value> OXSEED-8071 OXSEED-8071J</value></indexField><indexField><name>recovery_id_str</name><value>OXSEED-8071A2</value></indexField><indexField><name>toverify_boolean</name><value>false</value></indexField><indexField><name>update_boolean</name><value>false</value></indexField></indexFieldList></indexData><additionalDocumentInfo/></document></documentList><actionList/><processType>administration</processType><processPriority/><indexData><indexFieldList><indexField><name>pi_eingangsdatum_date</name><value>2011-04-15T22:29:28.231Z</value></indexField><indexField><name>pi_full_path</name><value>/Akte-Spedition/POD/Ablieferbeleg/2011/</value></indexField><indexField><name>pi_import_path_str</name><value>/mnt/shared/wackler/import@wackler.oxseed.net/data/pod/ablieferbeleg/extern/4017/201104152130/DD-Frachtbr_extern_20110415202651942.split</value></indexField><indexField><name>pi_inputchannel_str</name><value>import_pod_extern</value></indexField><indexField><name>pi_level_0</name><value>Akte-Spedition</value></indexField><indexField><name>pi_level_1</name><value>POD</value></indexField><indexField><name>pi_level_2</name><value>Ablieferbeleg</value></indexField><indexField><name>pi_level_3</name><value>2011</value></indexField><indexField><name>pi_mandant_str</name><value>wackler</value></indexField><indexField><name>pi_order_id_str</name><value>201104152229261441012FD2155D8F525BA0577DDDF0A2D36E1B4000000000642cda0e5</value></indexField><indexField><name>pi_process_id_str</name><value>201104152229282280a280a565622e4204a</value></indexField><indexField><name>pi_process_type_str</name><value>POD</value></indexField><indexField><name>pi_sm_status_str</name><value>finished</value></indexField><indexField><name>pi_stack_id_str</name><value>DD-Frachtbr_extern_20110415202651942.split_fileImport_working_20110415222858_1313201843_pod</value></indexField></indexFieldList></indexData><additionalProcessInfo/><systemMessages/></process><process><id>201104152229282810a280a56fec9cf8438</id><documentList><document><id>201104152229280190008BC35D0628B009A1C461B91D429917B65000000008482398ce6</id><idType/><actionList/><inputType/><documentType>import_protocol</documentType><indexData><indexFieldList><indexField><name>depot_number_str</name><value>4017</value></indexField><indexField><name>document_id_str</name><value>201104152229280190008BC35D0628B009A1C461B91D429917B65000000008482398ce6</value></indexField><indexField><name>document_type_str</name><value>Ablieferbeleg</value></indexField><indexField><name>dokumentennummer_str</name><value>41119648</value></indexField><indexField><name>export_boolean</name><value>true</value></indexField><indexField><name>input_file_name_str</name><value>/mnt/work/servicemix/working_directory/import/imported/wackler/DD-Frachtbr_extern_20110415202651942.split_fileImport_working_20110415222858_1313201843_pod_201104152229292085934/201104152229280190008BC35D0628B009A1C461B91D429917B65000000008482398ce6_19145149</value></indexField><indexField><name>page_count_int</name><value>2</value></indexField><indexField><name>recovery_id_ftxt</name><value> OXSEED-8071 OXSEED-8071J</value></indexField><indexField><name>recovery_id_str</name><value>OXSEED-8071A2</value></indexField><indexField><name>toverify_boolean</name><value>false</value></indexField><indexField><name>update_boolean</name><value>false</value></indexField></indexFieldList></indexData><additionalDocumentInfo/></document></documentList><actionList/><processType>administration</processType><processPriority/><indexData><indexFieldList><indexField><name>pi_eingangsdatum_date</name><value>2011-04-15T22:29:28.285Z</value></indexField><indexField><name>pi_full_path</name><value>/Akte-Spedition/POD/Ablieferbeleg/2011/</value></indexField><indexField><name>pi_import_path_str</name><value>/mnt/shared/wackler/import@wackler.oxseed.net/data/pod/ablieferbeleg/extern/4017/201104152130/DD-Frachtbr_extern_20110415202651942.split</value></indexField><indexField><name>pi_inputchannel_str</name><value>import_pod_extern</value></indexField><indexField><name>pi_level_0</name><value>Akte-Spedition</value></indexField><indexField><name>pi_level_1</name><value>POD</value></indexField><indexField><name>pi_level_2</name><value>Ablieferbeleg</value></indexField><indexField><name>pi_level_3</name><value>2011</value></indexField><indexField><name>pi_mandant_str</name><value>wackler</value></indexField><indexField><name>pi_order_id_str</name><value>201104152229261441012FD2155D8F525BA0577DDDF0A2D36E1B4000000000642cda0e5</value></indexField><indexField><name>pi_process_id_str</name><value>201104152229282810a280a56fec9cf8438</value></indexField><indexField><name>pi_process_type_str</name><value>POD</value></indexField><indexField><name>pi_sm_status_str</name><value>finished</value></indexField><indexField><name>pi_stack_id_str</name><value>DD-Frachtbr_extern_20110415202651942.split_fileImport_working_20110415222858_1313201843_pod</value></indexField></indexFieldList></indexData><additionalProcessInfo/><systemMessages/></process><process><id>201104152229282070a280a56ea55d98504</id><documentList><document><id>2011041522292632700087C8EFCD201F3F96F93A2275CA338B1F60000000079c15a238d</id><idType/><actionList/><inputType/><documentType>import_protocol</documentType><indexData><indexFieldList><indexField><name>depot_number_str</name><value>4017</value></indexField><indexField><name>document_id_str</name><value>2011041522292632700087C8EFCD201F3F96F93A2275CA338B1F60000000079c15a238d</value></indexField><indexField><name>document_type_str</name><value>Ablieferbeleg</value></indexField><indexField><name>dokumentennummer_str</name><value>41123130</value></indexField><indexField><name>export_boolean</name><value>true</value></indexField><indexField><name>input_file_name_str</name><value>/mnt/work/servicemix/working_directory/import/imported/wackler/DD-Frachtbr_extern_20110415202651942.split_fileImport_working_20110415222858_1313201843_pod_201104152229292085934/2011041522292632700087C8EFCD201F3F96F93A2275CA338B1F60000000079c15a238d_10264976</value></indexField><indexField><name>page_count_int</name><value>3</value></indexField><indexField><name>recovery_id_ftxt</name><value> OXSEED-8071 OXSEED-8071J</value></indexField><indexField><name>recovery_id_str</name><value>OXSEED-8071A2</value></indexField><indexField><name>toverify_boolean</name><value>false</value></indexField><indexField><name>update_boolean</name><value>false</value></indexField></indexFieldList></indexData><additionalDocumentInfo/></document></documentList><actionList/><processType>administration</processType><processPriority/><indexData><indexFieldList><indexField><name>pi_eingangsdatum_date</name><value>2011-04-15T22:29:28.210Z</value></indexField><indexField><name>pi_full_path</name><value>/Akte-Spedition/POD/Ablieferbeleg/2011/</value></indexField><indexField><name>pi_import_path_str</name><value>/mnt/shared/wackler/import@wackler.oxseed.net/data/pod/ablieferbeleg/extern/4017/201104152130/DD-Frachtbr_extern_20110415202651942.split</value></indexField><indexField><name>pi_inputchannel_str</name><value>import_pod_extern</value></indexField><indexField><name>pi_level_0</name><value>Akte-Spedition</value></indexField><indexField><name>pi_level_1</name><value>POD</value></indexField><indexField><name>pi_level_2</name><value>Ablieferbeleg</value></indexField><indexField><name>pi_level_3</name><value>2011</value></indexField><indexField><name>pi_mandant_str</name><value>wackler</value></indexField><indexField><name>pi_order_id_str</name><value>201104152229261441012FD2155D8F525BA0577DDDF0A2D36E1B4000000000642cda0e5</value></indexField><indexField><name>pi_process_id_str</name><value>201104152229282070a280a56ea55d98504</value></indexField><indexField><name>pi_process_type_str</name><value>POD</value></indexField><indexField><name>pi_sm_status_str</name><value>finished</value></indexField><indexField><name>pi_stack_id_str</name><value>DD-Frachtbr_extern_20110415202651942.split_fileImport_working_20110415222858_1313201843_pod</value></indexField></indexFieldList></indexData><additionalProcessInfo/><systemMessages/></process><process><id>201104152229282410a280a56e603f083b7</id><documentList><document><id>201104152229269810008A07B6AA0B3310D04BB18EE0BE47F1DB5000000008ee86dc4b0</id><idType/><actionList/><inputType/><documentType>import_protocol</documentType><indexData><indexFieldList><indexField><name>depot_number_str</name><value>4017</value></indexField><indexField><name>document_id_str</name><value>201104152229269810008A07B6AA0B3310D04BB18EE0BE47F1DB5000000008ee86dc4b0</value></indexField><indexField><name>document_type_str</name><value>Ablieferbeleg</value></indexField><indexField><name>dokumentennummer_str</name><value>41123560</value></indexField><indexField><name>export_boolean</name><value>true</value></indexField><indexField><name>input_file_name_str</name><value>/mnt/work/servicemix/working_directory/import/imported/wackler/DD-Frachtbr_extern_20110415202651942.split_fileImport_working_20110415222858_1313201843_pod_201104152229292085934/201104152229269810008A07B6AA0B3310D04BB18EE0BE47F1DB5000000008ee86dc4b0_10138057</value></indexField><indexField><name>page_count_int</name><value>3</value></indexField><indexField><name>recovery_id_ftxt</name><value> OXSEED-8071 OXSEED-8071J</value></indexField><indexField><name>recovery_id_str</name><value>OXSEED-8071A2</value></indexField><indexField><name>toverify_boolean</name><value>false</value></indexField><indexField><name>update_boolean</name><value>false</value></indexField></indexFieldList></indexData><additionalDocumentInfo/></document></documentList><actionList/><processType>administration</processType><processPriority/><indexData><indexFieldList><indexField><name>pi_eingangsdatum_date</name><value>2011-04-15T22:29:28.244Z</value></indexField><indexField><name>pi_full_path</name><value>/Akte-Spedition/POD/Ablieferbeleg/2011/</value></indexField><indexField><name>pi_import_path_str</name><value>/mnt/shared/wackler/import@wackler.oxseed.net/data/pod/ablieferbeleg/extern/4017/201104152130/DD-Frachtbr_extern_20110415202651942.split</value></indexField><indexField><name>pi_inputchannel_str</name><value>import_pod_extern</value></indexField><indexField><name>pi_level_0</name><value>Akte-Spedition</value></indexField><indexField><name>pi_level_1</name><value>POD</value></indexField><indexField><name>pi_level_2</name><value>Ablieferbeleg</value></indexField><indexField><name>pi_level_3</name><value>2011</value></indexField><indexField><name>pi_mandant_str</name><value>wackler</value></indexField><indexField><name>pi_order_id_str</name><value>201104152229261441012FD2155D8F525BA0577DDDF0A2D36E1B4000000000642cda0e5</value></indexField><indexField><name>pi_process_id_str</name><value>201104152229282410a280a56e603f083b7</value></indexField><indexField><name>pi_process_type_str</name><value>POD</value></indexField><indexField><name>pi_sm_status_str</name><value>finished</value></indexField><indexField><name>pi_stack_id_str</name><value>DD-Frachtbr_extern_20110415202651942.split_fileImport_working_20110415222858_1313201843_pod</value></indexField></indexFieldList></indexData><additionalProcessInfo/><systemMessages/></process><process><id>201104152229282140a280a564b06791545</id><documentList><document><id>20110415222926511000871A9E7D6A2DA7839FFFC8F4D36A2F87F000000008133ff0fef</id><idType/><actionList/><inputType/><documentType>import_protocol</documentType><indexData><indexFieldList><indexField><name>depot_number_str</name><value>4017</value></indexField><indexField><name>document_id_str</name><value>20110415222926511000871A9E7D6A2DA7839FFFC8F4D36A2F87F000000008133ff0fef</value></indexField><indexField><name>document_type_str</name><value>Ablieferbeleg</value></indexField><indexField><name>dokumentennummer_str</name><value>41123175</value></indexField><indexField><name>export_boolean</name><value>true</value></indexField><indexField><name>input_file_name_str</name><value>/mnt/work/servicemix/working_directory/import/imported/wackler/DD-Frachtbr_extern_20110415202651942.split_fileImport_working_20110415222858_1313201843_pod_201104152229292085934/20110415222926511000871A9E7D6A2DA7839FFFC8F4D36A2F87F000000008133ff0fef_75835045</value></indexField><indexField><name>page_count_int</name><value>3</value></indexField><indexField><name>recovery_id_ftxt</name><value> OXSEED-8071 OXSEED-8071J</value></indexField><indexField><name>recovery_id_str</name><value>OXSEED-8071A2</value></indexField><indexField><name>toverify_boolean</name><value>false</value></indexField><indexField><name>update_boolean</name><value>false</value></indexField></indexFieldList></indexData><additionalDocumentInfo/></document></documentList><actionList/><processType>administration</processType><processPriority/><indexData><indexFieldList><indexField><name>pi_eingangsdatum_date</name><value>2011-04-15T22:29:28.219Z</value></indexField><indexField><name>pi_full_path</name><value>/Akte-Spedition/POD/Ablieferbeleg/2011/</value></indexField><indexField><name>pi_import_path_str</name><value>/mnt/shared/wackler/import@wackler.oxseed.net/data/pod/ablieferbeleg/extern/4017/201104152130/DD-Frachtbr_extern_20110415202651942.split</value></indexField><indexField><name>pi_inputchannel_str</name><value>import_pod_extern</value></indexField><indexField><name>pi_level_0</name><value>Akte-Spedition</value></indexField><indexField><name>pi_level_1</name><value>POD</value></indexField><indexField><name>pi_level_2</name><value>Ablieferbeleg</value></indexField><indexField><name>pi_level_3</name><value>2011</value></indexField><indexField><name>pi_mandant_str</name><value>wackler</value></indexField><indexField><name>pi_order_id_str</name><value>201104152229261441012FD2155D8F525BA0577DDDF0A2D36E1B4000000000642cda0e5</value></indexField><indexField><name>pi_process_id_str</name><value>201104152229282140a280a564b06791545</value></indexField><indexField><name>pi_process_type_str</name><value>POD</value></indexField><indexField><name>pi_sm_status_str</name><value>finished</value></indexField><indexField><name>pi_stack_id_str</name><value>DD-Frachtbr_extern_20110415202651942.split_fileImport_working_20110415222858_1313201843_pod</value></indexField></indexFieldList></indexData><additionalProcessInfo/><systemMessages/></process><process><id>201104152229282690a280a56f5ff89510c</id><documentList><document><id>2011041522292774300088B52D39F26EC25922D1984F887306B490000000051a6378ada</id><idType/><actionList/><inputType/><documentType>import_protocol</documentType><indexData><indexFieldList><indexField><name>depot_number_str</name><value>4017</value></indexField><indexField><name>document_id_str</name><value>2011041522292774300088B52D39F26EC25922D1984F887306B490000000051a6378ada</value></indexField><indexField><name>document_type_str</name><value>Ablieferbeleg</value></indexField><indexField><name>dokumentennummer_str</name><value>41121345</value></indexField><indexField><name>export_boolean</name><value>true</value></indexField><indexField><name>input_file_name_str</name><value>/mnt/work/servicemix/working_directory/import/imported/wackler/DD-Frachtbr_extern_20110415202651942.split_fileImport_working_20110415222858_1313201843_pod_201104152229292085934/2011041522292774300088B52D39F26EC25922D1984F887306B490000000051a6378ada_19046999</value></indexField><indexField><name>page_count_int</name><value>2</value></indexField><indexField><name>recovery_id_ftxt</name><value> OXSEED-8071 OXSEED-8071J</value></indexField><indexField><name>recovery_id_str</name><value>OXSEED-8071A2</value></indexField><indexField><name>toverify_boolean</name><value>false</value></indexField><indexField><name>update_boolean</name><value>false</value></indexField></indexFieldList></indexData><additionalDocumentInfo/></document></documentList><actionList/><processType>administration</processType><processPriority/><indexData><indexFieldList><indexField><name>pi_eingangsdatum_date</name><value>2011-04-15T22:29:28.273Z</value></indexField><indexField><name>pi_full_path</name><value>/Akte-Spedition/POD/Ablieferbeleg/2011/</value></indexField><indexField><name>pi_import_path_str</name><value>/mnt/shared/wackler/import@wackler.oxseed.net/data/pod/ablieferbeleg/extern/4017/201104152130/DD-Frachtbr_extern_20110415202651942.split</value></indexField><indexField><name>pi_inputchannel_str</name><value>import_pod_extern</value></indexField><indexField><name>pi_level_0</name><value>Akte-Spedition</value></indexField><indexField><name>pi_level_1</name><value>POD</value></indexField><indexField><name>pi_level_2</name><value>Ablieferbeleg</value></indexField><indexField><name>pi_level_3</name><value>2011</value></indexField><indexField><name>pi_mandant_str</name><value>wackler</value></indexField><indexField><name>pi_order_id_str</name><value>201104152229261441012FD2155D8F525BA0577DDDF0A2D36E1B4000000000642cda0e5</value></indexField><indexField><name>pi_process_id_str</name><value>201104152229282690a280a56f5ff89510c</value></indexField><indexField><name>pi_process_type_str</name><value>POD</value></indexField><indexField><name>pi_sm_status_str</name><value>finished</value></indexField><indexField><name>pi_stack_id_str</name><value>DD-Frachtbr_extern_20110415202651942.split_fileImport_working_20110415222858_1313201843_pod</value></indexField></indexFieldList></indexData><additionalProcessInfo/><systemMessages/></process><process><id>201104152229282310a280a56ec04396f47</id><documentList><document><id>2011041522292679400083D67C1C5C5DACC960B4B75D53A56DD0700000000e554de6ed5</id><idType/><actionList/><inputType/><documentType>import_protocol</documentType><indexData><indexFieldList><indexField><name>depot_number_str</name><value>4017</value></indexField><indexField><name>document_id_str</name><value>2011041522292679400083D67C1C5C5DACC960B4B75D53A56DD0700000000e554de6ed5</value></indexField><indexField><name>document_type_str</name><value>Ablieferbeleg</value></indexField><indexField><name>dokumentennummer_str</name><value>41121362</value></indexField><indexField><name>export_boolean</name><value>true</value></indexField><indexField><name>input_file_name_str</name><value>/mnt/work/servicemix/working_directory/import/imported/wackler/DD-Frachtbr_extern_20110415202651942.split_fileImport_working_20110415222858_1313201843_pod_201104152229292085934/2011041522292679400083D67C1C5C5DACC960B4B75D53A56DD0700000000e554de6ed5_97157234</value></indexField><indexField><name>page_count_int</name><value>3</value></indexField><indexField><name>recovery_id_ftxt</name><value> OXSEED-8071 OXSEED-8071J</value></indexField><indexField><name>recovery_id_str</name><value>OXSEED-8071A2</value></indexField><indexField><name>toverify_boolean</name><value>false</value></indexField><indexField><name>update_boolean</name><value>false</value></indexField></indexFieldList></indexData><additionalDocumentInfo/></document></documentList><actionList/><processType>administration</processType><processPriority/><indexData><indexFieldList><indexField><name>pi_eingangsdatum_date</name><value>2011-04-15T22:29:28.235Z</value></indexField><indexField><name>pi_full_path</name><value>/Akte-Spedition/POD/Ablieferbeleg/2011/</value></indexField><indexField><name>pi_import_path_str</name><value>/mnt/shared/wackler/import@wackler.oxseed.net/data/pod/ablieferbeleg/extern/4017/201104152130/DD-Frachtbr_extern_20110415202651942.split</value></indexField><indexField><name>pi_inputchannel_str</name><value>import_pod_extern</value></indexField><indexField><name>pi_level_0</name><value>Akte-Spedition</value></indexField><indexField><name>pi_level_1</name><value>POD</value></indexField><indexField><name>pi_level_2</name><value>Ablieferbeleg</value></indexField><indexField><name>pi_level_3</name><value>2011</value></indexField><indexField><name>pi_mandant_str</name><value>wackler</value></indexField><indexField><name>pi_order_id_str</name><value>201104152229261441012FD2155D8F525BA0577DDDF0A2D36E1B4000000000642cda0e5</value></indexField><indexField><name>pi_process_id_str</name><value>201104152229282310a280a56ec04396f47</value></indexField><indexField><name>pi_process_type_str</name><value>POD</value></indexField><indexField><name>pi_sm_status_str</name><value>finished</value></indexField><indexField><name>pi_stack_id_str</name><value>DD-Frachtbr_extern_20110415202651942.split_fileImport_working_20110415222858_1313201843_pod</value></indexField></indexFieldList></indexData><additionalProcessInfo/><systemMessages/></process></processList><additionalStackInfo/></stack><actionList/><mandant>wackler</mandant><inputChannel/><exportChannel/><additionalOrderInfo/></ns2:order>