<?xml version="1.0" encoding="UTF-8"?><ns2:order xmlns:ns2="http://oxseed.com/data/order" xmlns:ns3="http://oxseed.com/data/commons/entrylist" xmlns:ns4="http://oxseed.com/data/extension/metadata" xmlns:ns5="http://oxseed.com/data/extension/orderdeps"><id>201104141300007831012A279ADD09308F0A382E5F11F73AD0E6A00000000ec40eb911f</id><stack><id>DD-Frachtbr_intern_20110414123806842.split_fileImport_working_20110414125922_814900847_pod</id><processList><process><id>201104141300023730a280a568545a5c1fb</id><documentList><document><id>2011041413000194100085672A7E2C605FB80F9FFF6A16C12E0CC000000004b0526aae8</id><idType/><actionList/><inputType/><documentType>import_protocol</documentType><indexData><indexFieldList><indexField><name>document_id_str</name><value>2011041413000194100085672A7E2C605FB80F9FFF6A16C12E0CC000000004b0526aae8</value></indexField><indexField><name>document_type_str</name><value>Ablieferbeleg</value></indexField><indexField><name>dokumentennummer_str</name><value>41122124</value></indexField><indexField><name>export_boolean</name><value>false</value></indexField><indexField><name>input_file_name_str</name><value>/mnt/work/servicemix/working_directory/import/imported/wackler/DD-Frachtbr_intern_20110414123806842.split_fileImport_working_20110414125922_814900847_pod_201104141300037827949/2011041413000194100085672A7E2C605FB80F9FFF6A16C12E0CC000000004b0526aae8_20750075</value></indexField><indexField><name>page_count_int</name><value>1</value></indexField><indexField><name>recovery_id_ftxt</name><value> OXSEED-8071 OXSEED-8071J</value></indexField><indexField><name>recovery_id_str</name><value>OXSEED-8071A2</value></indexField><indexField><name>toverify_boolean</name><value>false</value></indexField><indexField><name>update_boolean</name><value>false</value></indexField></indexFieldList></indexData><additionalDocumentInfo/></document></documentList><actionList/><processType>administration</processType><processPriority/><indexData><indexFieldList><indexField><name>pi_eingangsdatum_date</name><value>2011-04-14T13:00:02.376Z</value></indexField><indexField><name>pi_full_path</name><value>/Akte-Spedition/POD/Ablieferbeleg/2011/</value></indexField><indexField><name>pi_import_path_str</name><value>/mnt/shared/wackler/import@wackler.oxseed.net/data/pod/ablieferbeleg/intern/201104141240/DD-Frachtbr_intern_20110414123806842.split</value></indexField><indexField><name>pi_inputchannel_str</name><value>import_pod</value></indexField><indexField><name>pi_level_0</name><value>Akte-Spedition</value></indexField><indexField><name>pi_level_1</name><value>POD</value></indexField><indexField><name>pi_level_2</name><value>Ablieferbeleg</value></indexField><indexField><name>pi_level_3</name><value>2011</value></indexField><indexField><name>pi_mandant_str</name><value>wackler</value></indexField><indexField><name>pi_order_id_str</name><value>201104141300007831012A279ADD09308F0A382E5F11F73AD0E6A00000000ec40eb911f</value></indexField><indexField><name>pi_process_id_str</name><value>201104141300023730a280a568545a5c1fb</value></indexField><indexField><name>pi_process_type_str</name><value>POD</value></indexField><indexField><name>pi_sm_status_str</name><value>finished</value></indexField><indexField><name>pi_stack_id_str</name><value>DD-Frachtbr_intern_20110414123806842.split_fileImport_working_20110414125922_814900847_pod</value></indexField></indexFieldList></indexData><additionalProcessInfo/><systemMessages/></process><process><id>201104141300023490a280a563116b09290</id><documentList><document><id>20110414130001538000860BEBE878EF08F607CF31B808EE4B248000000006fccc16b4f</id><idType/><actionList/><inputType/><documentType>import_protocol</documentType><indexData><indexFieldList><indexField><name>document_id_str</name><value>20110414130001538000860BEBE878EF08F607CF31B808EE4B248000000006fccc16b4f</value></indexField><indexField><name>document_type_str</name><value>Ablieferbeleg</value></indexField><indexField><name>dokumentennummer_str</name><value>41122177</value></indexField><indexField><name>export_boolean</name><value>false</value></indexField><indexField><name>input_file_name_str</name><value>/mnt/work/servicemix/working_directory/import/imported/wackler/DD-Frachtbr_intern_20110414123806842.split_fileImport_working_20110414125922_814900847_pod_201104141300037827949/20110414130001538000860BEBE878EF08F607CF31B808EE4B248000000006fccc16b4f_17651637</value></indexField><indexField><name>page_count_int</name><value>1</value></indexField><indexField><name>recovery_id_ftxt</name><value> OXSEED-8071 OXSEED-8071J</value></indexField><indexField><name>recovery_id_str</name><value>OXSEED-8071A2</value></indexField><indexField><name>toverify_boolean</name><value>false</value></indexField><indexField><name>update_boolean</name><value>false</value></indexField></indexFieldList></indexData><additionalDocumentInfo/></document></documentList><actionList/><processType>administration</processType><processPriority/><indexData><indexFieldList><indexField><name>pi_eingangsdatum_date</name><value>2011-04-14T13:00:02.352Z</value></indexField><indexField><name>pi_full_path</name><value>/Akte-Spedition/POD/Ablieferbeleg/2011/</value></indexField><indexField><name>pi_import_path_str</name><value>/mnt/shared/wackler/import@wackler.oxseed.net/data/pod/ablieferbeleg/intern/201104141240/DD-Frachtbr_intern_20110414123806842.split</value></indexField><indexField><name>pi_inputchannel_str</name><value>import_pod</value></indexField><indexField><name>pi_level_0</name><value>Akte-Spedition</value></indexField><indexField><name>pi_level_1</name><value>POD</value></indexField><indexField><name>pi_level_2</name><value>Ablieferbeleg</value></indexField><indexField><name>pi_level_3</name><value>2011</value></indexField><indexField><name>pi_mandant_str</name><value>wackler</value></indexField><indexField><name>pi_order_id_str</name><value>201104141300007831012A279ADD09308F0A382E5F11F73AD0E6A00000000ec40eb911f</value></indexField><indexField><name>pi_process_id_str</name><value>201104141300023490a280a563116b09290</value></indexField><indexField><name>pi_process_type_str</name><value>POD</value></indexField><indexField><name>pi_sm_status_str</name><value>finished</value></indexField><indexField><name>pi_stack_id_str</name><value>DD-Frachtbr_intern_20110414123806842.split_fileImport_working_20110414125922_814900847_pod</value></indexField></indexFieldList></indexData><additionalProcessInfo/><systemMessages/></process><process><id>201104141300023190a280a56a7869f7d42</id><documentList><document><id>201104141300009990008D1EBD3D19FC436910FC7E8A54F8F338200000000cc3e4cbb7a</id><idType/><actionList/><inputType/><documentType>import_protocol</documentType><indexData><indexFieldList><indexField><name>document_id_str</name><value>201104141300009990008D1EBD3D19FC436910FC7E8A54F8F338200000000cc3e4cbb7a</value></indexField><indexField><name>document_type_str</name><value>Ablieferbeleg</value></indexField><indexField><name>dokumentennummer_str</name><value>41122328</value></indexField><indexField><name>export_boolean</name><value>false</value></indexField><indexField><name>input_file_name_str</name><value>/mnt/work/servicemix/working_directory/import/imported/wackler/DD-Frachtbr_intern_20110414123806842.split_fileImport_working_20110414125922_814900847_pod_201104141300037827949/201104141300009990008D1EBD3D19FC436910FC7E8A54F8F338200000000cc3e4cbb7a_16509446</value></indexField><indexField><name>page_count_int</name><value>1</value></indexField><indexField><name>recovery_id_ftxt</name><value> OXSEED-8071 OXSEED-8071J</value></indexField><indexField><name>recovery_id_str</name><value>OXSEED-8071A2</value></indexField><indexField><name>toverify_boolean</name><value>false</value></indexField><indexField><name>update_boolean</name><value>false</value></indexField></indexFieldList></indexData><additionalDocumentInfo/></document></documentList><actionList/><processType>administration</processType><processPriority/><indexData><indexFieldList><indexField><name>pi_eingangsdatum_date</name><value>2011-04-14T13:00:02.322Z</value></indexField><indexField><name>pi_full_path</name><value>/Akte-Spedition/POD/Ablieferbeleg/2011/</value></indexField><indexField><name>pi_import_path_str</name><value>/mnt/shared/wackler/import@wackler.oxseed.net/data/pod/ablieferbeleg/intern/201104141240/DD-Frachtbr_intern_20110414123806842.split</value></indexField><indexField><name>pi_inputchannel_str</name><value>import_pod</value></indexField><indexField><name>pi_level_0</name><value>Akte-Spedition</value></indexField><indexField><name>pi_level_1</name><value>POD</value></indexField><indexField><name>pi_level_2</name><value>Ablieferbeleg</value></indexField><indexField><name>pi_level_3</name><value>2011</value></indexField><indexField><name>pi_mandant_str</name><value>wackler</value></indexField><indexField><name>pi_order_id_str</name><value>201104141300007831012A279ADD09308F0A382E5F11F73AD0E6A00000000ec40eb911f</value></indexField><indexField><name>pi_process_id_str</name><value>201104141300023190a280a56a7869f7d42</value></indexField><indexField><name>pi_process_type_str</name><value>POD</value></indexField><indexField><name>pi_sm_status_str</name><value>finished</value></indexField><indexField><name>pi_stack_id_str</name><value>DD-Frachtbr_intern_20110414123806842.split_fileImport_working_20110414125922_814900847_pod</value></indexField></indexFieldList></indexData><additionalProcessInfo/><systemMessages/></process><process><id>201104141300023340a280a56219315980c</id><documentList><document><id>201104141300012720008A9E0715D7E4CADB24EB4261664B619D4000000002c8108657e</id><idType/><actionList/><inputType/><documentType>import_protocol</documentType><indexData><indexFieldList><indexField><name>document_id_str</name><value>201104141300012720008A9E0715D7E4CADB24EB4261664B619D4000000002c8108657e</value></indexField><indexField><name>document_type_str</name><value>Ablieferbeleg</value></indexField><indexField><name>dokumentennummer_str</name><value>41110832</value></indexField><indexField><name>export_boolean</name><value>false</value></indexField><indexField><name>input_file_name_str</name><value>/mnt/work/servicemix/working_directory/import/imported/wackler/DD-Frachtbr_intern_20110414123806842.split_fileImport_working_20110414125922_814900847_pod_201104141300037827949/201104141300012720008A9E0715D7E4CADB24EB4261664B619D4000000002c8108657e_14199044</value></indexField><indexField><name>page_count_int</name><value>1</value></indexField><indexField><name>recovery_id_ftxt</name><value> OXSEED-8071 OXSEED-8071J</value></indexField><indexField><name>recovery_id_str</name><value>OXSEED-8071A2</value></indexField><indexField><name>toverify_boolean</name><value>false</value></indexField><indexField><name>update_boolean</name><value>false</value></indexField></indexFieldList></indexData><additionalDocumentInfo/></document></documentList><actionList/><processType>administration</processType><processPriority/><indexData><indexFieldList><indexField><name>pi_eingangsdatum_date</name><value>2011-04-14T13:00:02.337Z</value></indexField><indexField><name>pi_full_path</name><value>/Akte-Spedition/POD/Ablieferbeleg/2011/</value></indexField><indexField><name>pi_import_path_str</name><value>/mnt/shared/wackler/import@wackler.oxseed.net/data/pod/ablieferbeleg/intern/201104141240/DD-Frachtbr_intern_20110414123806842.split</value></indexField><indexField><name>pi_inputchannel_str</name><value>import_pod</value></indexField><indexField><name>pi_level_0</name><value>Akte-Spedition</value></indexField><indexField><name>pi_level_1</name><value>POD</value></indexField><indexField><name>pi_level_2</name><value>Ablieferbeleg</value></indexField><indexField><name>pi_level_3</name><value>2011</value></indexField><indexField><name>pi_mandant_str</name><value>wackler</value></indexField><indexField><name>pi_order_id_str</name><value>201104141300007831012A279ADD09308F0A382E5F11F73AD0E6A00000000ec40eb911f</value></indexField><indexField><name>pi_process_id_str</name><value>201104141300023340a280a56219315980c</value></indexField><indexField><name>pi_process_type_str</name><value>POD</value></indexField><indexField><name>pi_sm_status_str</name><value>finished</value></indexField><indexField><name>pi_stack_id_str</name><value>DD-Frachtbr_intern_20110414123806842.split_fileImport_working_20110414125922_814900847_pod</value></indexField></indexFieldList></indexData><additionalProcessInfo/><systemMessages/></process><process><id>201104141300023460a280a5658dc13f8ef</id><documentList><document><id>201104141300014850008D46AFE3973A9746946F45CFE85500656000000006a3d60ba06</id><idType/><actionList/><inputType/><documentType>import_protocol</documentType><indexData><indexFieldList><indexField><name>document_id_str</name><value>201104141300014850008D46AFE3973A9746946F45CFE85500656000000006a3d60ba06</value></indexField><indexField><name>document_type_str</name><value>Ablieferbeleg</value></indexField><indexField><name>dokumentennummer_str</name><value>41122182</value></indexField><indexField><name>export_boolean</name><value>false</value></indexField><indexField><name>input_file_name_str</name><value>/mnt/work/servicemix/working_directory/import/imported/wackler/DD-Frachtbr_intern_20110414123806842.split_fileImport_working_20110414125922_814900847_pod_201104141300037827949/201104141300014850008D46AFE3973A9746946F45CFE85500656000000006a3d60ba06_13682677</value></indexField><indexField><name>page_count_int</name><value>1</value></indexField><indexField><name>recovery_id_ftxt</name><value> OXSEED-8071 OXSEED-8071J</value></indexField><indexField><name>recovery_id_str</name><value>OXSEED-8071A2</value></indexField><indexField><name>toverify_boolean</name><value>false</value></indexField><indexField><name>update_boolean</name><value>false</value></indexField></indexFieldList></indexData><additionalDocumentInfo/></document></documentList><actionList/><processType>administration</processType><processPriority/><indexData><indexFieldList><indexField><name>pi_eingangsdatum_date</name><value>2011-04-14T13:00:02.349Z</value></indexField><indexField><name>pi_full_path</name><value>/Akte-Spedition/POD/Ablieferbeleg/2011/</value></indexField><indexField><name>pi_import_path_str</name><value>/mnt/shared/wackler/import@wackler.oxseed.net/data/pod/ablieferbeleg/intern/201104141240/DD-Frachtbr_intern_20110414123806842.split</value></indexField><indexField><name>pi_inputchannel_str</name><value>import_pod</value></indexField><indexField><name>pi_level_0</name><value>Akte-Spedition</value></indexField><indexField><name>pi_level_1</name><value>POD</value></indexField><indexField><name>pi_level_2</name><value>Ablieferbeleg</value></indexField><indexField><name>pi_level_3</name><value>2011</value></indexField><indexField><name>pi_mandant_str</name><value>wackler</value></indexField><indexField><name>pi_order_id_str</name><value>201104141300007831012A279ADD09308F0A382E5F11F73AD0E6A00000000ec40eb911f</value></indexField><indexField><name>pi_process_id_str</name><value>201104141300023460a280a5658dc13f8ef</value></indexField><indexField><name>pi_process_type_str</name><value>POD</value></indexField><indexField><name>pi_sm_status_str</name><value>finished</value></indexField><indexField><name>pi_stack_id_str</name><value>DD-Frachtbr_intern_20110414123806842.split_fileImport_working_20110414125922_814900847_pod</value></indexField></indexFieldList></indexData><additionalProcessInfo/><systemMessages/></process><process><id>201104141300023670a280a56623f6a29f6</id><documentList><document><id>201104141300018440008078A34286D81F4722E42B24C9859F3FA00000000898c12f951</id><idType/><actionList/><inputType/><documentType>import_protocol</documentType><indexData><indexFieldList><indexField><name>document_id_str</name><value>201104141300018440008078A34286D81F4722E42B24C9859F3FA00000000898c12f951</value></indexField><indexField><name>document_type_str</name><value>Ablieferbeleg</value></indexField><indexField><name>dokumentennummer_str</name><value>41122144</value></indexField><indexField><name>export_boolean</name><value>false</value></indexField><indexField><name>input_file_name_str</name><value>/mnt/work/servicemix/working_directory/import/imported/wackler/DD-Frachtbr_intern_20110414123806842.split_fileImport_working_20110414125922_814900847_pod_201104141300037827949/201104141300018440008078A34286D81F4722E42B24C9859F3FA00000000898c12f951_12090749</value></indexField><indexField><name>page_count_int</name><value>1</value></indexField><indexField><name>recovery_id_ftxt</name><value> OXSEED-8071 OXSEED-8071J</value></indexField><indexField><name>recovery_id_str</name><value>OXSEED-8071A2</value></indexField><indexField><name>toverify_boolean</name><value>false</value></indexField><indexField><name>update_boolean</name><value>false</value></indexField></indexFieldList></indexData><additionalDocumentInfo/></document></documentList><actionList/><processType>administration</processType><processPriority/><indexData><indexFieldList><indexField><name>pi_eingangsdatum_date</name><value>2011-04-14T13:00:02.370Z</value></indexField><indexField><name>pi_full_path</name><value>/Akte-Spedition/POD/Ablieferbeleg/2011/</value></indexField><indexField><name>pi_import_path_str</name><value>/mnt/shared/wackler/import@wackler.oxseed.net/data/pod/ablieferbeleg/intern/201104141240/DD-Frachtbr_intern_20110414123806842.split</value></indexField><indexField><name>pi_inputchannel_str</name><value>import_pod</value></indexField><indexField><name>pi_level_0</name><value>Akte-Spedition</value></indexField><indexField><name>pi_level_1</name><value>POD</value></indexField><indexField><name>pi_level_2</name><value>Ablieferbeleg</value></indexField><indexField><name>pi_level_3</name><value>2011</value></indexField><indexField><name>pi_mandant_str</name><value>wackler</value></indexField><indexField><name>pi_order_id_str</name><value>201104141300007831012A279ADD09308F0A382E5F11F73AD0E6A00000000ec40eb911f</value></indexField><indexField><name>pi_process_id_str</name><value>201104141300023670a280a56623f6a29f6</value></indexField><indexField><name>pi_process_type_str</name><value>POD</value></indexField><indexField><name>pi_sm_status_str</name><value>finished</value></indexField><indexField><name>pi_stack_id_str</name><value>DD-Frachtbr_intern_20110414123806842.split_fileImport_working_20110414125922_814900847_pod</value></indexField></indexFieldList></indexData><additionalProcessInfo/><systemMessages/></process><process><id>201104141300023930a280a56dc6f69f36b</id><documentList><document><id>20110414130002252000815569A95EFF77243F18569A54AD5BC0B00000000abfb34248d</id><idType/><actionList/><inputType/><documentType>import_protocol</documentType><indexData><indexFieldList><indexField><name>document_id_str</name><value>20110414130002252000815569A95EFF77243F18569A54AD5BC0B00000000abfb34248d</value></indexField><indexField><name>document_type_str</name><value>Ablieferbeleg</value></indexField><indexField><name>dokumentennummer_str</name><value>41122084</value></indexField><indexField><name>export_boolean</name><value>false</value></indexField><indexField><name>input_file_name_str</name><value>/mnt/work/servicemix/working_directory/import/imported/wackler/DD-Frachtbr_intern_20110414123806842.split_fileImport_working_20110414125922_814900847_pod_201104141300037827949/20110414130002252000815569A95EFF77243F18569A54AD5BC0B00000000abfb34248d_93046128</value></indexField><indexField><name>page_count_int</name><value>1</value></indexField><indexField><name>recovery_id_ftxt</name><value> OXSEED-8071 OXSEED-8071J</value></indexField><indexField><name>recovery_id_str</name><value>OXSEED-8071A2</value></indexField><indexField><name>toverify_boolean</name><value>false</value></indexField><indexField><name>update_boolean</name><value>false</value></indexField></indexFieldList></indexData><additionalDocumentInfo/></document></documentList><actionList/><processType>administration</processType><processPriority/><indexData><indexFieldList><indexField><name>pi_eingangsdatum_date</name><value>2011-04-14T13:00:02.396Z</value></indexField><indexField><name>pi_full_path</name><value>/Akte-Spedition/POD/Ablieferbeleg/2011/</value></indexField><indexField><name>pi_import_path_str</name><value>/mnt/shared/wackler/import@wackler.oxseed.net/data/pod/ablieferbeleg/intern/201104141240/DD-Frachtbr_intern_20110414123806842.split</value></indexField><indexField><name>pi_inputchannel_str</name><value>import_pod</value></indexField><indexField><name>pi_level_0</name><value>Akte-Spedition</value></indexField><indexField><name>pi_level_1</name><value>POD</value></indexField><indexField><name>pi_level_2</name><value>Ablieferbeleg</value></indexField><indexField><name>pi_level_3</name><value>2011</value></indexField><indexField><name>pi_mandant_str</name><value>wackler</value></indexField><indexField><name>pi_order_id_str</name><value>201104141300007831012A279ADD09308F0A382E5F11F73AD0E6A00000000ec40eb911f</value></indexField><indexField><name>pi_process_id_str</name><value>201104141300023930a280a56dc6f69f36b</value></indexField><indexField><name>pi_process_type_str</name><value>POD</value></indexField><indexField><name>pi_sm_status_str</name><value>finished</value></indexField><indexField><name>pi_stack_id_str</name><value>DD-Frachtbr_intern_20110414123806842.split_fileImport_working_20110414125922_814900847_pod</value></indexField></indexFieldList></indexData><additionalProcessInfo/><systemMessages/></process><process><id>201104141300023370a280a5644a7afca02</id><documentList><document><id>201104141300013260008B0996B9122563BBCE807EEE43CB2D12B000000006b0bd6b1e0</id><idType/><actionList/><inputType/><documentType>import_protocol</documentType><indexData><indexFieldList><indexField><name>document_id_str</name><value>201104141300013260008B0996B9122563BBCE807EEE43CB2D12B000000006b0bd6b1e0</value></indexField><indexField><name>document_type_str</name><value>Ablieferbeleg</value></indexField><indexField><name>dokumentennummer_str</name><value>41122236</value></indexField><indexField><name>export_boolean</name><value>false</value></indexField><indexField><name>input_file_name_str</name><value>/mnt/work/servicemix/working_directory/import/imported/wackler/DD-Frachtbr_intern_20110414123806842.split_fileImport_working_20110414125922_814900847_pod_201104141300037827949/201104141300013260008B0996B9122563BBCE807EEE43CB2D12B000000006b0bd6b1e0_83790140</value></indexField><indexField><name>page_count_int</name><value>1</value></indexField><indexField><name>recovery_id_ftxt</name><value> OXSEED-8071 OXSEED-8071J</value></indexField><indexField><name>recovery_id_str</name><value>OXSEED-8071A2</value></indexField><indexField><name>toverify_boolean</name><value>false</value></indexField><indexField><name>update_boolean</name><value>false</value></indexField></indexFieldList></indexData><additionalDocumentInfo/></document></documentList><actionList/><processType>administration</processType><processPriority/><indexData><indexFieldList><indexField><name>pi_eingangsdatum_date</name><value>2011-04-14T13:00:02.340Z</value></indexField><indexField><name>pi_full_path</name><value>/Akte-Spedition/POD/Ablieferbeleg/2011/</value></indexField><indexField><name>pi_import_path_str</name><value>/mnt/shared/wackler/import@wackler.oxseed.net/data/pod/ablieferbeleg/intern/201104141240/DD-Frachtbr_intern_20110414123806842.split</value></indexField><indexField><name>pi_inputchannel_str</name><value>import_pod</value></indexField><indexField><name>pi_level_0</name><value>Akte-Spedition</value></indexField><indexField><name>pi_level_1</name><value>POD</value></indexField><indexField><name>pi_level_2</name><value>Ablieferbeleg</value></indexField><indexField><name>pi_level_3</name><value>2011</value></indexField><indexField><name>pi_mandant_str</name><value>wackler</value></indexField><indexField><name>pi_order_id_str</name><value>201104141300007831012A279ADD09308F0A382E5F11F73AD0E6A00000000ec40eb911f</value></indexField><indexField><name>pi_process_id_str</name><value>201104141300023370a280a5644a7afca02</value></indexField><indexField><name>pi_process_type_str</name><value>POD</value></indexField><indexField><name>pi_sm_status_str</name><value>finished</value></indexField><indexField><name>pi_stack_id_str</name><value>DD-Frachtbr_intern_20110414123806842.split_fileImport_working_20110414125922_814900847_pod</value></indexField></indexFieldList></indexData><additionalProcessInfo/><systemMessages/></process><process><id>201104141300023700a280a569416e92576</id><documentList><document><id>201104141300018920008B024E853D9D222BD40EC963E9F18F5F50000000015cf766644</id><idType/><actionList/><inputType/><documentType>import_protocol</documentType><indexData><indexFieldList><indexField><name>document_id_str</name><value>201104141300018920008B024E853D9D222BD40EC963E9F18F5F50000000015cf766644</value></indexField><indexField><name>document_type_str</name><value>Ablieferbeleg</value></indexField><indexField><name>dokumentennummer_str</name><value>41122062</value></indexField><indexField><name>export_boolean</name><value>false</value></indexField><indexField><name>input_file_name_str</name><value>/mnt/work/servicemix/working_directory/import/imported/wackler/DD-Frachtbr_intern_20110414123806842.split_fileImport_working_20110414125922_814900847_pod_201104141300037827949/201104141300018920008B024E853D9D222BD40EC963E9F18F5F50000000015cf766644_27431589</value></indexField><indexField><name>page_count_int</name><value>1</value></indexField><indexField><name>recovery_id_ftxt</name><value> OXSEED-8071 OXSEED-8071J</value></indexField><indexField><name>recovery_id_str</name><value>OXSEED-8071A2</value></indexField><indexField><name>toverify_boolean</name><value>false</value></indexField><indexField><name>update_boolean</name><value>false</value></indexField></indexFieldList></indexData><additionalDocumentInfo/></document></documentList><actionList/><processType>administration</processType><processPriority/><indexData><indexFieldList><indexField><name>pi_eingangsdatum_date</name><value>2011-04-14T13:00:02.373Z</value></indexField><indexField><name>pi_full_path</name><value>/Akte-Spedition/POD/Ablieferbeleg/2011/</value></indexField><indexField><name>pi_import_path_str</name><value>/mnt/shared/wackler/import@wackler.oxseed.net/data/pod/ablieferbeleg/intern/201104141240/DD-Frachtbr_intern_20110414123806842.split</value></indexField><indexField><name>pi_inputchannel_str</name><value>import_pod</value></indexField><indexField><name>pi_level_0</name><value>Akte-Spedition</value></indexField><indexField><name>pi_level_1</name><value>POD</value></indexField><indexField><name>pi_level_2</name><value>Ablieferbeleg</value></indexField><indexField><name>pi_level_3</name><value>2011</value></indexField><indexField><name>pi_mandant_str</name><value>wackler</value></indexField><indexField><name>pi_order_id_str</name><value>201104141300007831012A279ADD09308F0A382E5F11F73AD0E6A00000000ec40eb911f</value></indexField><indexField><name>pi_process_id_str</name><value>201104141300023700a280a569416e92576</value></indexField><indexField><name>pi_process_type_str</name><value>POD</value></indexField><indexField><name>pi_sm_status_str</name><value>finished</value></indexField><indexField><name>pi_stack_id_str</name><value>DD-Frachtbr_intern_20110414123806842.split_fileImport_working_20110414125922_814900847_pod</value></indexField></indexFieldList></indexData><additionalProcessInfo/><systemMessages/></process><process><id>201104141300023640a280a56df1000e8b1</id><documentList><document><id>201104141300017920008B1F523CEF15C4F0958F3E5910C178BAA000000005b49742bbb</id><idType/><actionList/><inputType/><documentType>import_protocol</documentType><indexData><indexFieldList><indexField><name>document_id_str</name><value>201104141300017920008B1F523CEF15C4F0958F3E5910C178BAA000000005b49742bbb</value></indexField><indexField><name>document_type_str</name><value>Ablieferbeleg</value></indexField><indexField><name>dokumentennummer_str</name><value>41122155</value></indexField><indexField><name>export_boolean</name><value>false</value></indexField><indexField><name>input_file_name_str</name><value>/mnt/work/servicemix/working_directory/import/imported/wackler/DD-Frachtbr_intern_20110414123806842.split_fileImport_working_20110414125922_814900847_pod_201104141300037827949/201104141300017920008B1F523CEF15C4F0958F3E5910C178BAA000000005b49742bbb_13740541</value></indexField><indexField><name>page_count_int</name><value>1</value></indexField><indexField><name>recovery_id_ftxt</name><value> OXSEED-8071 OXSEED-8071J</value></indexField><indexField><name>recovery_id_str</name><value>OXSEED-8071A2</value></indexField><indexField><name>toverify_boolean</name><value>false</value></indexField><indexField><name>update_boolean</name><value>false</value></indexField></indexFieldList></indexData><additionalDocumentInfo/></document></documentList><actionList/><processType>administration</processType><processPriority/><indexData><indexFieldList><indexField><name>pi_eingangsdatum_date</name><value>2011-04-14T13:00:02.367Z</value></indexField><indexField><name>pi_full_path</name><value>/Akte-Spedition/POD/Ablieferbeleg/2011/</value></indexField><indexField><name>pi_import_path_str</name><value>/mnt/shared/wackler/import@wackler.oxseed.net/data/pod/ablieferbeleg/intern/201104141240/DD-Frachtbr_intern_20110414123806842.split</value></indexField><indexField><name>pi_inputchannel_str</name><value>import_pod</value></indexField><indexField><name>pi_level_0</name><value>Akte-Spedition</value></indexField><indexField><name>pi_level_1</name><value>POD</value></indexField><indexField><name>pi_level_2</name><value>Ablieferbeleg</value></indexField><indexField><name>pi_level_3</name><value>2011</value></indexField><indexField><name>pi_mandant_str</name><value>wackler</value></indexField><indexField><name>pi_order_id_str</name><value>201104141300007831012A279ADD09308F0A382E5F11F73AD0E6A00000000ec40eb911f</value></indexField><indexField><name>pi_process_id_str</name><value>201104141300023640a280a56df1000e8b1</value></indexField><indexField><name>pi_process_type_str</name><value>POD</value></indexField><indexField><name>pi_sm_status_str</name><value>finished</value></indexField><indexField><name>pi_stack_id_str</name><value>DD-Frachtbr_intern_20110414123806842.split_fileImport_working_20110414125922_814900847_pod</value></indexField></indexFieldList></indexData><additionalProcessInfo/><systemMessages/></process><process><id>201104141300023580a280a56c7dd6e61b4</id><documentList><document><id>201104141300016900008295FAA1C6E3EE5EA204AA175F8FD40AC000000005132563abb</id><idType/><actionList/><inputType/><documentType>import_protocol</documentType><indexData><indexFieldList><indexField><name>document_id_str</name><value>201104141300016900008295FAA1C6E3EE5EA204AA175F8FD40AC000000005132563abb</value></indexField><indexField><name>document_type_str</name><value>Ablieferbeleg</value></indexField><indexField><name>dokumentennummer_str</name><value>41122127</value></indexField><indexField><name>export_boolean</name><value>false</value></indexField><indexField><name>input_file_name_str</name><value>/mnt/work/servicemix/working_directory/import/imported/wackler/DD-Frachtbr_intern_20110414123806842.split_fileImport_working_20110414125922_814900847_pod_201104141300037827949/201104141300016900008295FAA1C6E3EE5EA204AA175F8FD40AC000000005132563abb_16472972</value></indexField><indexField><name>page_count_int</name><value>1</value></indexField><indexField><name>recovery_id_ftxt</name><value> OXSEED-8071 OXSEED-8071J</value></indexField><indexField><name>recovery_id_str</name><value>OXSEED-8071A2</value></indexField><indexField><name>toverify_boolean</name><value>false</value></indexField><indexField><name>update_boolean</name><value>false</value></indexField></indexFieldList></indexData><additionalDocumentInfo/></document></documentList><actionList/><processType>administration</processType><processPriority/><indexData><indexFieldList><indexField><name>pi_eingangsdatum_date</name><value>2011-04-14T13:00:02.361Z</value></indexField><indexField><name>pi_full_path</name><value>/Akte-Spedition/POD/Ablieferbeleg/2011/</value></indexField><indexField><name>pi_import_path_str</name><value>/mnt/shared/wackler/import@wackler.oxseed.net/data/pod/ablieferbeleg/intern/201104141240/DD-Frachtbr_intern_20110414123806842.split</value></indexField><indexField><name>pi_inputchannel_str</name><value>import_pod</value></indexField><indexField><name>pi_level_0</name><value>Akte-Spedition</value></indexField><indexField><name>pi_level_1</name><value>POD</value></indexField><indexField><name>pi_level_2</name><value>Ablieferbeleg</value></indexField><indexField><name>pi_level_3</name><value>2011</value></indexField><indexField><name>pi_mandant_str</name><value>wackler</value></indexField><indexField><name>pi_order_id_str</name><value>201104141300007831012A279ADD09308F0A382E5F11F73AD0E6A00000000ec40eb911f</value></indexField><indexField><name>pi_process_id_str</name><value>201104141300023580a280a56c7dd6e61b4</value></indexField><indexField><name>pi_process_type_str</name><value>POD</value></indexField><indexField><name>pi_sm_status_str</name><value>finished</value></indexField><indexField><name>pi_stack_id_str</name><value>DD-Frachtbr_intern_20110414123806842.split_fileImport_working_20110414125922_814900847_pod</value></indexField></indexFieldList></indexData><additionalProcessInfo/><systemMessages/></process><process><id>201104141300023220a280a56afd6ad967d</id><documentList><document><id>201104141300010520008244B5366E3B96771B1C97BBC8441C75E00000000973a12891d</id><idType/><actionList/><inputType/><documentType>import_protocol</documentType><indexData><indexFieldList><indexField><name>document_id_str</name><value>201104141300010520008244B5366E3B96771B1C97BBC8441C75E00000000973a12891d</value></indexField><indexField><name>document_type_str</name><value>Ablieferbeleg</value></indexField><indexField><name>dokumentennummer_str</name><value>41122252</value></indexField><indexField><name>export_boolean</name><value>false</value></indexField><indexField><name>input_file_name_str</name><value>/mnt/work/servicemix/working_directory/import/imported/wackler/DD-Frachtbr_intern_20110414123806842.split_fileImport_working_20110414125922_814900847_pod_201104141300037827949/201104141300010520008244B5366E3B96771B1C97BBC8441C75E00000000973a12891d_87193364</value></indexField><indexField><name>page_count_int</name><value>1</value></indexField><indexField><name>recovery_id_ftxt</name><value> OXSEED-8071 OXSEED-8071J</value></indexField><indexField><name>recovery_id_str</name><value>OXSEED-8071A2</value></indexField><indexField><name>toverify_boolean</name><value>false</value></indexField><indexField><name>update_boolean</name><value>false</value></indexField></indexFieldList></indexData><additionalDocumentInfo/></document></documentList><actionList/><processType>administration</processType><processPriority/><indexData><indexFieldList><indexField><name>pi_eingangsdatum_date</name><value>2011-04-14T13:00:02.325Z</value></indexField><indexField><name>pi_full_path</name><value>/Akte-Spedition/POD/Ablieferbeleg/2011/</value></indexField><indexField><name>pi_import_path_str</name><value>/mnt/shared/wackler/import@wackler.oxseed.net/data/pod/ablieferbeleg/intern/201104141240/DD-Frachtbr_intern_20110414123806842.split</value></indexField><indexField><name>pi_inputchannel_str</name><value>import_pod</value></indexField><indexField><name>pi_level_0</name><value>Akte-Spedition</value></indexField><indexField><name>pi_level_1</name><value>POD</value></indexField><indexField><name>pi_level_2</name><value>Ablieferbeleg</value></indexField><indexField><name>pi_level_3</name><value>2011</value></indexField><indexField><name>pi_mandant_str</name><value>wackler</value></indexField><indexField><name>pi_order_id_str</name><value>201104141300007831012A279ADD09308F0A382E5F11F73AD0E6A00000000ec40eb911f</value></indexField><indexField><name>pi_process_id_str</name><value>201104141300023220a280a56afd6ad967d</value></indexField><indexField><name>pi_process_type_str</name><value>POD</value></indexField><indexField><name>pi_sm_status_str</name><value>finished</value></indexField><indexField><name>pi_stack_id_str</name><value>DD-Frachtbr_intern_20110414123806842.split_fileImport_working_20110414125922_814900847_pod</value></indexField></indexFieldList></indexData><additionalProcessInfo/><systemMessages/></process><process><id>201104141300023520a280a56e720414e8c</id><documentList><document><id>201104141300015880008E9B525E47AF446823BB3479BA84448DB0000000010509dd45b</id><idType/><actionList/><inputType/><documentType>import_protocol</documentType><indexData><indexFieldList><indexField><name>document_id_str</name><value>201104141300015880008E9B525E47AF446823BB3479BA84448DB0000000010509dd45b</value></indexField><indexField><name>document_type_str</name><value>Ablieferbeleg</value></indexField><indexField><name>dokumentennummer_str</name><value>41122169</value></indexField><indexField><name>export_boolean</name><value>false</value></indexField><indexField><name>input_file_name_str</name><value>/mnt/work/servicemix/working_directory/import/imported/wackler/DD-Frachtbr_intern_20110414123806842.split_fileImport_working_20110414125922_814900847_pod_201104141300037827949/201104141300015880008E9B525E47AF446823BB3479BA84448DB0000000010509dd45b_12425969</value></indexField><indexField><name>page_count_int</name><value>1</value></indexField><indexField><name>recovery_id_ftxt</name><value> OXSEED-8071 OXSEED-8071J</value></indexField><indexField><name>recovery_id_str</name><value>OXSEED-8071A2</value></indexField><indexField><name>toverify_boolean</name><value>false</value></indexField><indexField><name>update_boolean</name><value>false</value></indexField></indexFieldList></indexData><additionalDocumentInfo/></document></documentList><actionList/><processType>administration</processType><processPriority/><indexData><indexFieldList><indexField><name>pi_eingangsdatum_date</name><value>2011-04-14T13:00:02.355Z</value></indexField><indexField><name>pi_full_path</name><value>/Akte-Spedition/POD/Ablieferbeleg/2011/</value></indexField><indexField><name>pi_import_path_str</name><value>/mnt/shared/wackler/import@wackler.oxseed.net/data/pod/ablieferbeleg/intern/201104141240/DD-Frachtbr_intern_20110414123806842.split</value></indexField><indexField><name>pi_inputchannel_str</name><value>import_pod</value></indexField><indexField><name>pi_level_0</name><value>Akte-Spedition</value></indexField><indexField><name>pi_level_1</name><value>POD</value></indexField><indexField><name>pi_level_2</name><value>Ablieferbeleg</value></indexField><indexField><name>pi_level_3</name><value>2011</value></indexField><indexField><name>pi_mandant_str</name><value>wackler</value></indexField><indexField><name>pi_order_id_str</name><value>201104141300007831012A279ADD09308F0A382E5F11F73AD0E6A00000000ec40eb911f</value></indexField><indexField><name>pi_process_id_str</name><value>201104141300023520a280a56e720414e8c</value></indexField><indexField><name>pi_process_type_str</name><value>POD</value></indexField><indexField><name>pi_sm_status_str</name><value>finished</value></indexField><indexField><name>pi_stack_id_str</name><value>DD-Frachtbr_intern_20110414123806842.split_fileImport_working_20110414125922_814900847_pod</value></indexField></indexFieldList></indexData><additionalProcessInfo/><systemMessages/></process><process><id>201104141300023310a280a56f6cb0b2f67</id><documentList><document><id>201104141300012200008EA320345C86ED9902E5C217247F91F5B00000000d30fcea3d8</id><idType/><actionList/><inputType/><documentType>import_protocol</documentType><indexData><indexFieldList><indexField><name>document_id_str</name><value>201104141300012200008EA320345C86ED9902E5C217247F91F5B00000000d30fcea3d8</value></indexField><indexField><name>document_type_str</name><value>Ablieferbeleg</value></indexField><indexField><name>dokumentennummer_str</name><value>41122246</value></indexField><indexField><name>export_boolean</name><value>false</value></indexField><indexField><name>input_file_name_str</name><value>/mnt/work/servicemix/working_directory/import/imported/wackler/DD-Frachtbr_intern_20110414123806842.split_fileImport_working_20110414125922_814900847_pod_201104141300037827949/201104141300012200008EA320345C86ED9902E5C217247F91F5B00000000d30fcea3d8_20560106</value></indexField><indexField><name>page_count_int</name><value>1</value></indexField><indexField><name>recovery_id_ftxt</name><value> OXSEED-8071 OXSEED-8071J</value></indexField><indexField><name>recovery_id_str</name><value>OXSEED-8071A2</value></indexField><indexField><name>toverify_boolean</name><value>false</value></indexField><indexField><name>update_boolean</name><value>false</value></indexField></indexFieldList></indexData><additionalDocumentInfo/></document></documentList><actionList/><processType>administration</processType><processPriority/><indexData><indexFieldList><indexField><name>pi_eingangsdatum_date</name><value>2011-04-14T13:00:02.334Z</value></indexField><indexField><name>pi_full_path</name><value>/Akte-Spedition/POD/Ablieferbeleg/2011/</value></indexField><indexField><name>pi_import_path_str</name><value>/mnt/shared/wackler/import@wackler.oxseed.net/data/pod/ablieferbeleg/intern/201104141240/DD-Frachtbr_intern_20110414123806842.split</value></indexField><indexField><name>pi_inputchannel_str</name><value>import_pod</value></indexField><indexField><name>pi_level_0</name><value>Akte-Spedition</value></indexField><indexField><name>pi_level_1</name><value>POD</value></indexField><indexField><name>pi_level_2</name><value>Ablieferbeleg</value></indexField><indexField><name>pi_level_3</name><value>2011</value></indexField><indexField><name>pi_mandant_str</name><value>wackler</value></indexField><indexField><name>pi_order_id_str</name><value>201104141300007831012A279ADD09308F0A382E5F11F73AD0E6A00000000ec40eb911f</value></indexField><indexField><name>pi_process_id_str</name><value>201104141300023310a280a56f6cb0b2f67</value></indexField><indexField><name>pi_process_type_str</name><value>POD</value></indexField><indexField><name>pi_sm_status_str</name><value>finished</value></indexField><indexField><name>pi_stack_id_str</name><value>DD-Frachtbr_intern_20110414123806842.split_fileImport_working_20110414125922_814900847_pod</value></indexField></indexFieldList></indexData><additionalProcessInfo/><systemMessages/></process><process><id>201104141300023890a280a56237fb4c73b</id><documentList><document><id>2011041413000219700081510836A9BDF62CF9152DCA1DBBADDB800000000c62a5b9580</id><idType/><actionList/><inputType/><documentType>import_protocol</documentType><indexData><indexFieldList><indexField><name>document_id_str</name><value>2011041413000219700081510836A9BDF62CF9152DCA1DBBADDB800000000c62a5b9580</value></indexField><indexField><name>document_type_str</name><value>Ablieferbeleg</value></indexField><indexField><name>dokumentennummer_str</name><value>41122087</value></indexField><indexField><name>export_boolean</name><value>false</value></indexField><indexField><name>input_file_name_str</name><value>/mnt/work/servicemix/working_directory/import/imported/wackler/DD-Frachtbr_intern_20110414123806842.split_fileImport_working_20110414125922_814900847_pod_201104141300037827949/2011041413000219700081510836A9BDF62CF9152DCA1DBBADDB800000000c62a5b9580_14505644</value></indexField><indexField><name>page_count_int</name><value>1</value></indexField><indexField><name>recovery_id_ftxt</name><value> OXSEED-8071 OXSEED-8071J</value></indexField><indexField><name>recovery_id_str</name><value>OXSEED-8071A2</value></indexField><indexField><name>toverify_boolean</name><value>false</value></indexField><indexField><name>update_boolean</name><value>false</value></indexField></indexFieldList></indexData><additionalDocumentInfo/></document></documentList><actionList/><processType>administration</processType><processPriority/><indexData><indexFieldList><indexField><name>pi_eingangsdatum_date</name><value>2011-04-14T13:00:02.392Z</value></indexField><indexField><name>pi_full_path</name><value>/Akte-Spedition/POD/Ablieferbeleg/2011/</value></indexField><indexField><name>pi_import_path_str</name><value>/mnt/shared/wackler/import@wackler.oxseed.net/data/pod/ablieferbeleg/intern/201104141240/DD-Frachtbr_intern_20110414123806842.split</value></indexField><indexField><name>pi_inputchannel_str</name><value>import_pod</value></indexField><indexField><name>pi_level_0</name><value>Akte-Spedition</value></indexField><indexField><name>pi_level_1</name><value>POD</value></indexField><indexField><name>pi_level_2</name><value>Ablieferbeleg</value></indexField><indexField><name>pi_level_3</name><value>2011</value></indexField><indexField><name>pi_mandant_str</name><value>wackler</value></indexField><indexField><name>pi_order_id_str</name><value>201104141300007831012A279ADD09308F0A382E5F11F73AD0E6A00000000ec40eb911f</value></indexField><indexField><name>pi_process_id_str</name><value>201104141300023890a280a56237fb4c73b</value></indexField><indexField><name>pi_process_type_str</name><value>POD</value></indexField><indexField><name>pi_sm_status_str</name><value>finished</value></indexField><indexField><name>pi_stack_id_str</name><value>DD-Frachtbr_intern_20110414123806842.split_fileImport_working_20110414125922_814900847_pod</value></indexField></indexFieldList></indexData><additionalProcessInfo/><systemMessages/></process><process><id>201104141300023160a280a56a4bc391f4c</id><documentList><document><id>2011041413000094800084A4EE97BEBE7C2DD1A5431CED9DE064F00000000e51693c4f3</id><idType/><actionList/><inputType/><documentType>import_protocol</documentType><indexData><indexFieldList><indexField><name>document_id_str</name><value>2011041413000094800084A4EE97BEBE7C2DD1A5431CED9DE064F00000000e51693c4f3</value></indexField><indexField><name>document_type_str</name><value>Ablieferbeleg</value></indexField><indexField><name>dokumentennummer_str</name><value>41122318</value></indexField><indexField><name>export_boolean</name><value>false</value></indexField><indexField><name>input_file_name_str</name><value>/mnt/work/servicemix/working_directory/import/imported/wackler/DD-Frachtbr_intern_20110414123806842.split_fileImport_working_20110414125922_814900847_pod_201104141300037827949/2011041413000094800084A4EE97BEBE7C2DD1A5431CED9DE064F00000000e51693c4f3_10742924</value></indexField><indexField><name>page_count_int</name><value>1</value></indexField><indexField><name>recovery_id_ftxt</name><value> OXSEED-8071 OXSEED-8071J</value></indexField><indexField><name>recovery_id_str</name><value>OXSEED-8071A2</value></indexField><indexField><name>toverify_boolean</name><value>false</value></indexField><indexField><name>update_boolean</name><value>false</value></indexField></indexFieldList></indexData><additionalDocumentInfo/></document></documentList><actionList/><processType>administration</processType><processPriority/><indexData><indexFieldList><indexField><name>pi_eingangsdatum_date</name><value>2011-04-14T13:00:02.319Z</value></indexField><indexField><name>pi_full_path</name><value>/Akte-Spedition/POD/Ablieferbeleg/2011/</value></indexField><indexField><name>pi_import_path_str</name><value>/mnt/shared/wackler/import@wackler.oxseed.net/data/pod/ablieferbeleg/intern/201104141240/DD-Frachtbr_intern_20110414123806842.split</value></indexField><indexField><name>pi_inputchannel_str</name><value>import_pod</value></indexField><indexField><name>pi_level_0</name><value>Akte-Spedition</value></indexField><indexField><name>pi_level_1</name><value>POD</value></indexField><indexField><name>pi_level_2</name><value>Ablieferbeleg</value></indexField><indexField><name>pi_level_3</name><value>2011</value></indexField><indexField><name>pi_mandant_str</name><value>wackler</value></indexField><indexField><name>pi_order_id_str</name><value>201104141300007831012A279ADD09308F0A382E5F11F73AD0E6A00000000ec40eb911f</value></indexField><indexField><name>pi_process_id_str</name><value>201104141300023160a280a56a4bc391f4c</value></indexField><indexField><name>pi_process_type_str</name><value>POD</value></indexField><indexField><name>pi_sm_status_str</name><value>finished</value></indexField><indexField><name>pi_stack_id_str</name><value>DD-Frachtbr_intern_20110414123806842.split_fileImport_working_20110414125922_814900847_pod</value></indexField></indexFieldList></indexData><additionalProcessInfo/><systemMessages/></process><process><id>201104141300023820a280a5653e17c5ff8</id><documentList><document><id>2011041413000209300080DE0E10BB0D7F4D97EC28E1FF80E8BCB0000000029d793e659</id><idType/><actionList/><inputType/><documentType>import_protocol</documentType><indexData><indexFieldList><indexField><name>document_id_str</name><value>2011041413000209300080DE0E10BB0D7F4D97EC28E1FF80E8BCB0000000029d793e659</value></indexField><indexField><name>document_type_str</name><value>Ablieferbeleg</value></indexField><indexField><name>dokumentennummer_str</name><value>41122107</value></indexField><indexField><name>export_boolean</name><value>false</value></indexField><indexField><name>input_file_name_str</name><value>/mnt/work/servicemix/working_directory/import/imported/wackler/DD-Frachtbr_intern_20110414123806842.split_fileImport_working_20110414125922_814900847_pod_201104141300037827949/2011041413000209300080DE0E10BB0D7F4D97EC28E1FF80E8BCB0000000029d793e659_20451047</value></indexField><indexField><name>page_count_int</name><value>1</value></indexField><indexField><name>recovery_id_ftxt</name><value> OXSEED-8071 OXSEED-8071J</value></indexField><indexField><name>recovery_id_str</name><value>OXSEED-8071A2</value></indexField><indexField><name>toverify_boolean</name><value>false</value></indexField><indexField><name>update_boolean</name><value>false</value></indexField></indexFieldList></indexData><additionalDocumentInfo/></document></documentList><actionList/><processType>administration</processType><processPriority/><indexData><indexFieldList><indexField><name>pi_eingangsdatum_date</name><value>2011-04-14T13:00:02.385Z</value></indexField><indexField><name>pi_full_path</name><value>/Akte-Spedition/POD/Ablieferbeleg/2011/</value></indexField><indexField><name>pi_import_path_str</name><value>/mnt/shared/wackler/import@wackler.oxseed.net/data/pod/ablieferbeleg/intern/201104141240/DD-Frachtbr_intern_20110414123806842.split</value></indexField><indexField><name>pi_inputchannel_str</name><value>import_pod</value></indexField><indexField><name>pi_level_0</name><value>Akte-Spedition</value></indexField><indexField><name>pi_level_1</name><value>POD</value></indexField><indexField><name>pi_level_2</name><value>Ablieferbeleg</value></indexField><indexField><name>pi_level_3</name><value>2011</value></indexField><indexField><name>pi_mandant_str</name><value>wackler</value></indexField><indexField><name>pi_order_id_str</name><value>201104141300007831012A279ADD09308F0A382E5F11F73AD0E6A00000000ec40eb911f</value></indexField><indexField><name>pi_process_id_str</name><value>201104141300023820a280a5653e17c5ff8</value></indexField><indexField><name>pi_process_type_str</name><value>POD</value></indexField><indexField><name>pi_sm_status_str</name><value>finished</value></indexField><indexField><name>pi_stack_id_str</name><value>DD-Frachtbr_intern_20110414123806842.split_fileImport_working_20110414125922_814900847_pod</value></indexField></indexFieldList></indexData><additionalProcessInfo/><systemMessages/></process><process><id>201104141300023960a280a56e5331f0103</id><documentList><document><id>2011041413000230800086EC442D7688E8CEB4C51EE0DA3ABA7FD000000000341cd4f3c</id><idType/><actionList/><inputType/><documentType>import_protocol</documentType><indexData><indexFieldList><indexField><name>document_id_str</name><value>2011041413000230800086EC442D7688E8CEB4C51EE0DA3ABA7FD000000000341cd4f3c</value></indexField><indexField><name>document_type_str</name><value>Ablieferbeleg</value></indexField><indexField><name>dokumentennummer_str</name><value>41122065</value></indexField><indexField><name>export_boolean</name><value>false</value></indexField><indexField><name>input_file_name_str</name><value>/mnt/work/servicemix/working_directory/import/imported/wackler/DD-Frachtbr_intern_20110414123806842.split_fileImport_working_20110414125922_814900847_pod_201104141300037827949/2011041413000230800086EC442D7688E8CEB4C51EE0DA3ABA7FD000000000341cd4f3c_11355822</value></indexField><indexField><name>page_count_int</name><value>4</value></indexField><indexField><name>recovery_id_ftxt</name><value> OXSEED-8071 OXSEED-8071J</value></indexField><indexField><name>recovery_id_str</name><value>OXSEED-8071A2</value></indexField><indexField><name>toverify_boolean</name><value>false</value></indexField><indexField><name>update_boolean</name><value>false</value></indexField></indexFieldList></indexData><additionalDocumentInfo/></document></documentList><actionList/><processType>administration</processType><processPriority/><indexData><indexFieldList><indexField><name>pi_eingangsdatum_date</name><value>2011-04-14T13:00:02.399Z</value></indexField><indexField><name>pi_full_path</name><value>/Akte-Spedition/POD/Ablieferbeleg/2011/</value></indexField><indexField><name>pi_import_path_str</name><value>/mnt/shared/wackler/import@wackler.oxseed.net/data/pod/ablieferbeleg/intern/201104141240/DD-Frachtbr_intern_20110414123806842.split</value></indexField><indexField><name>pi_inputchannel_str</name><value>import_pod</value></indexField><indexField><name>pi_level_0</name><value>Akte-Spedition</value></indexField><indexField><name>pi_level_1</name><value>POD</value></indexField><indexField><name>pi_level_2</name><value>Ablieferbeleg</value></indexField><indexField><name>pi_level_3</name><value>2011</value></indexField><indexField><name>pi_mandant_str</name><value>wackler</value></indexField><indexField><name>pi_order_id_str</name><value>201104141300007831012A279ADD09308F0A382E5F11F73AD0E6A00000000ec40eb911f</value></indexField><indexField><name>pi_process_id_str</name><value>201104141300023960a280a56e5331f0103</value></indexField><indexField><name>pi_process_type_str</name><value>POD</value></indexField><indexField><name>pi_sm_status_str</name><value>finished</value></indexField><indexField><name>pi_stack_id_str</name><value>DD-Frachtbr_intern_20110414123806842.split_fileImport_working_20110414125922_814900847_pod</value></indexField></indexFieldList></indexData><additionalProcessInfo/><systemMessages/></process><process><id>201104141300023280a280a566dafb52b80</id><documentList><document><id>20110414130001160000849C9D27BF3793B9DD496E3C2D94A6C8600000000578ae173e2</id><idType/><actionList/><inputType/><documentType>import_protocol</documentType><indexData><indexFieldList><indexField><name>document_id_str</name><value>20110414130001160000849C9D27BF3793B9DD496E3C2D94A6C8600000000578ae173e2</value></indexField><indexField><name>document_type_str</name><value>Ablieferbeleg</value></indexField><indexField><name>dokumentennummer_str</name><value>41122247</value></indexField><indexField><name>export_boolean</name><value>false</value></indexField><indexField><name>input_file_name_str</name><value>/mnt/work/servicemix/working_directory/import/imported/wackler/DD-Frachtbr_intern_20110414123806842.split_fileImport_working_20110414125922_814900847_pod_201104141300037827949/20110414130001160000849C9D27BF3793B9DD496E3C2D94A6C8600000000578ae173e2_38112415</value></indexField><indexField><name>page_count_int</name><value>1</value></indexField><indexField><name>recovery_id_ftxt</name><value> OXSEED-8071 OXSEED-8071J</value></indexField><indexField><name>recovery_id_str</name><value>OXSEED-8071A2</value></indexField><indexField><name>toverify_boolean</name><value>false</value></indexField><indexField><name>update_boolean</name><value>false</value></indexField></indexFieldList></indexData><additionalDocumentInfo/></document></documentList><actionList/><processType>administration</processType><processPriority/><indexData><indexFieldList><indexField><name>pi_eingangsdatum_date</name><value>2011-04-14T13:00:02.331Z</value></indexField><indexField><name>pi_full_path</name><value>/Akte-Spedition/POD/Ablieferbeleg/2011/</value></indexField><indexField><name>pi_import_path_str</name><value>/mnt/shared/wackler/import@wackler.oxseed.net/data/pod/ablieferbeleg/intern/201104141240/DD-Frachtbr_intern_20110414123806842.split</value></indexField><indexField><name>pi_inputchannel_str</name><value>import_pod</value></indexField><indexField><name>pi_level_0</name><value>Akte-Spedition</value></indexField><indexField><name>pi_level_1</name><value>POD</value></indexField><indexField><name>pi_level_2</name><value>Ablieferbeleg</value></indexField><indexField><name>pi_level_3</name><value>2011</value></indexField><indexField><name>pi_mandant_str</name><value>wackler</value></indexField><indexField><name>pi_order_id_str</name><value>201104141300007831012A279ADD09308F0A382E5F11F73AD0E6A00000000ec40eb911f</value></indexField><indexField><name>pi_process_id_str</name><value>201104141300023280a280a566dafb52b80</value></indexField><indexField><name>pi_process_type_str</name><value>POD</value></indexField><indexField><name>pi_sm_status_str</name><value>finished</value></indexField><indexField><name>pi_stack_id_str</name><value>DD-Frachtbr_intern_20110414123806842.split_fileImport_working_20110414125922_814900847_pod</value></indexField></indexFieldList></indexData><additionalProcessInfo/><systemMessages/></process><process><id>201104141300023100a280a56ab86693de6</id><documentList><document><id>201104141300008450008497A18A9F112D21D98D5E6295D3A78420000000035f2b170d3</id><idType/><actionList/><inputType/><documentType>import_protocol</documentType><indexData><indexFieldList><indexField><name>document_id_str</name><value>201104141300008450008497A18A9F112D21D98D5E6295D3A78420000000035f2b170d3</value></indexField><indexField><name>document_type_str</name><value>Ablieferbeleg</value></indexField><indexField><name>dokumentennummer_str</name><value>41122345</value></indexField><indexField><name>export_boolean</name><value>false</value></indexField><indexField><name>input_file_name_str</name><value>/mnt/work/servicemix/working_directory/import/imported/wackler/DD-Frachtbr_intern_20110414123806842.split_fileImport_working_20110414125922_814900847_pod_201104141300037827949/201104141300008450008497A18A9F112D21D98D5E6295D3A78420000000035f2b170d3_46780931</value></indexField><indexField><name>page_count_int</name><value>1</value></indexField><indexField><name>recovery_id_ftxt</name><value> OXSEED-8071 OXSEED-8071J</value></indexField><indexField><name>recovery_id_str</name><value>OXSEED-8071A2</value></indexField><indexField><name>toverify_boolean</name><value>false</value></indexField><indexField><name>update_boolean</name><value>false</value></indexField></indexFieldList></indexData><additionalDocumentInfo/></document></documentList><actionList/><processType>administration</processType><processPriority/><indexData><indexFieldList><indexField><name>pi_eingangsdatum_date</name><value>2011-04-14T13:00:02.313Z</value></indexField><indexField><name>pi_full_path</name><value>/Akte-Spedition/POD/Ablieferbeleg/2011/</value></indexField><indexField><name>pi_import_path_str</name><value>/mnt/shared/wackler/import@wackler.oxseed.net/data/pod/ablieferbeleg/intern/201104141240/DD-Frachtbr_intern_20110414123806842.split</value></indexField><indexField><name>pi_inputchannel_str</name><value>import_pod</value></indexField><indexField><name>pi_level_0</name><value>Akte-Spedition</value></indexField><indexField><name>pi_level_1</name><value>POD</value></indexField><indexField><name>pi_level_2</name><value>Ablieferbeleg</value></indexField><indexField><name>pi_level_3</name><value>2011</value></indexField><indexField><name>pi_mandant_str</name><value>wackler</value></indexField><indexField><name>pi_order_id_str</name><value>201104141300007831012A279ADD09308F0A382E5F11F73AD0E6A00000000ec40eb911f</value></indexField><indexField><name>pi_process_id_str</name><value>201104141300023100a280a56ab86693de6</value></indexField><indexField><name>pi_process_type_str</name><value>POD</value></indexField><indexField><name>pi_sm_status_str</name><value>finished</value></indexField><indexField><name>pi_stack_id_str</name><value>DD-Frachtbr_intern_20110414123806842.split_fileImport_working_20110414125922_814900847_pod</value></indexField></indexFieldList></indexData><additionalProcessInfo/><systemMessages/></process><process><id>201104141300023430a280a56ee9bc9c77b</id><documentList><document><id>201104141300014320008BA43654E1504815DA4F27C372E8B2FD900000000a988782fd3</id><idType/><actionList/><inputType/><documentType>import_protocol</documentType><indexData><indexFieldList><indexField><name>document_id_str</name><value>201104141300014320008BA43654E1504815DA4F27C372E8B2FD900000000a988782fd3</value></indexField><indexField><name>document_type_str</name><value>Ablieferbeleg</value></indexField><indexField><name>dokumentennummer_str</name><value>41122183</value></indexField><indexField><name>export_boolean</name><value>false</value></indexField><indexField><name>input_file_name_str</name><value>/mnt/work/servicemix/working_directory/import/imported/wackler/DD-Frachtbr_intern_20110414123806842.split_fileImport_working_20110414125922_814900847_pod_201104141300037827949/201104141300014320008BA43654E1504815DA4F27C372E8B2FD900000000a988782fd3_14531458</value></indexField><indexField><name>page_count_int</name><value>1</value></indexField><indexField><name>recovery_id_ftxt</name><value> OXSEED-8071 OXSEED-8071J</value></indexField><indexField><name>recovery_id_str</name><value>OXSEED-8071A2</value></indexField><indexField><name>toverify_boolean</name><value>false</value></indexField><indexField><name>update_boolean</name><value>false</value></indexField></indexFieldList></indexData><additionalDocumentInfo/></document></documentList><actionList/><processType>administration</processType><processPriority/><indexData><indexFieldList><indexField><name>pi_eingangsdatum_date</name><value>2011-04-14T13:00:02.346Z</value></indexField><indexField><name>pi_full_path</name><value>/Akte-Spedition/POD/Ablieferbeleg/2011/</value></indexField><indexField><name>pi_import_path_str</name><value>/mnt/shared/wackler/import@wackler.oxseed.net/data/pod/ablieferbeleg/intern/201104141240/DD-Frachtbr_intern_20110414123806842.split</value></indexField><indexField><name>pi_inputchannel_str</name><value>import_pod</value></indexField><indexField><name>pi_level_0</name><value>Akte-Spedition</value></indexField><indexField><name>pi_level_1</name><value>POD</value></indexField><indexField><name>pi_level_2</name><value>Ablieferbeleg</value></indexField><indexField><name>pi_level_3</name><value>2011</value></indexField><indexField><name>pi_mandant_str</name><value>wackler</value></indexField><indexField><name>pi_order_id_str</name><value>201104141300007831012A279ADD09308F0A382E5F11F73AD0E6A00000000ec40eb911f</value></indexField><indexField><name>pi_process_id_str</name><value>201104141300023430a280a56ee9bc9c77b</value></indexField><indexField><name>pi_process_type_str</name><value>POD</value></indexField><indexField><name>pi_sm_status_str</name><value>finished</value></indexField><indexField><name>pi_stack_id_str</name><value>DD-Frachtbr_intern_20110414123806842.split_fileImport_working_20110414125922_814900847_pod</value></indexField></indexFieldList></indexData><additionalProcessInfo/><systemMessages/></process><process><id>201104141300023400a280a5649f38ebd16</id><documentList><document><id>201104141300013780008DAB8D58F89251BBAEC4EE526DB358E79000000002292684fb2</id><idType/><actionList/><inputType/><documentType>import_protocol</documentType><indexData><indexFieldList><indexField><name>document_id_str</name><value>201104141300013780008DAB8D58F89251BBAEC4EE526DB358E79000000002292684fb2</value></indexField><indexField><name>document_type_str</name><value>Ablieferbeleg</value></indexField><indexField><name>dokumentennummer_str</name><value>41122233</value></indexField><indexField><name>export_boolean</name><value>false</value></indexField><indexField><name>input_file_name_str</name><value>/mnt/work/servicemix/working_directory/import/imported/wackler/DD-Frachtbr_intern_20110414123806842.split_fileImport_working_20110414125922_814900847_pod_201104141300037827949/201104141300013780008DAB8D58F89251BBAEC4EE526DB358E79000000002292684fb2_19849978</value></indexField><indexField><name>page_count_int</name><value>1</value></indexField><indexField><name>recovery_id_ftxt</name><value> OXSEED-8071 OXSEED-8071J</value></indexField><indexField><name>recovery_id_str</name><value>OXSEED-8071A2</value></indexField><indexField><name>toverify_boolean</name><value>false</value></indexField><indexField><name>update_boolean</name><value>false</value></indexField></indexFieldList></indexData><additionalDocumentInfo/></document></documentList><actionList/><processType>administration</processType><processPriority/><indexData><indexFieldList><indexField><name>pi_eingangsdatum_date</name><value>2011-04-14T13:00:02.343Z</value></indexField><indexField><name>pi_full_path</name><value>/Akte-Spedition/POD/Ablieferbeleg/2011/</value></indexField><indexField><name>pi_import_path_str</name><value>/mnt/shared/wackler/import@wackler.oxseed.net/data/pod/ablieferbeleg/intern/201104141240/DD-Frachtbr_intern_20110414123806842.split</value></indexField><indexField><name>pi_inputchannel_str</name><value>import_pod</value></indexField><indexField><name>pi_level_0</name><value>Akte-Spedition</value></indexField><indexField><name>pi_level_1</name><value>POD</value></indexField><indexField><name>pi_level_2</name><value>Ablieferbeleg</value></indexField><indexField><name>pi_level_3</name><value>2011</value></indexField><indexField><name>pi_mandant_str</name><value>wackler</value></indexField><indexField><name>pi_order_id_str</name><value>201104141300007831012A279ADD09308F0A382E5F11F73AD0E6A00000000ec40eb911f</value></indexField><indexField><name>pi_process_id_str</name><value>201104141300023400a280a5649f38ebd16</value></indexField><indexField><name>pi_process_type_str</name><value>POD</value></indexField><indexField><name>pi_sm_status_str</name><value>finished</value></indexField><indexField><name>pi_stack_id_str</name><value>DD-Frachtbr_intern_20110414123806842.split_fileImport_working_20110414125922_814900847_pod</value></indexField></indexFieldList></indexData><additionalProcessInfo/><systemMessages/></process><process><id>201104141300023250a280a56456aac18a8</id><documentList><document><id>20110414130001108000869095496073BDB27F139443FE6C6A26D000000005d54537870</id><idType/><actionList/><inputType/><documentType>import_protocol</documentType><indexData><indexFieldList><indexField><name>document_id_str</name><value>20110414130001108000869095496073BDB27F139443FE6C6A26D000000005d54537870</value></indexField><indexField><name>document_type_str</name><value>Ablieferbeleg</value></indexField><indexField><name>dokumentennummer_str</name><value>41122251</value></indexField><indexField><name>export_boolean</name><value>false</value></indexField><indexField><name>input_file_name_str</name><value>/mnt/work/servicemix/working_directory/import/imported/wackler/DD-Frachtbr_intern_20110414123806842.split_fileImport_working_20110414125922_814900847_pod_201104141300037827949/20110414130001108000869095496073BDB27F139443FE6C6A26D000000005d54537870_90457292</value></indexField><indexField><name>page_count_int</name><value>2</value></indexField><indexField><name>recovery_id_ftxt</name><value> OXSEED-8071 OXSEED-8071J</value></indexField><indexField><name>recovery_id_str</name><value>OXSEED-8071A2</value></indexField><indexField><name>toverify_boolean</name><value>false</value></indexField><indexField><name>update_boolean</name><value>false</value></indexField></indexFieldList></indexData><additionalDocumentInfo/></document></documentList><actionList/><processType>administration</processType><processPriority/><indexData><indexFieldList><indexField><name>pi_eingangsdatum_date</name><value>2011-04-14T13:00:02.328Z</value></indexField><indexField><name>pi_full_path</name><value>/Akte-Spedition/POD/Ablieferbeleg/2011/</value></indexField><indexField><name>pi_import_path_str</name><value>/mnt/shared/wackler/import@wackler.oxseed.net/data/pod/ablieferbeleg/intern/201104141240/DD-Frachtbr_intern_20110414123806842.split</value></indexField><indexField><name>pi_inputchannel_str</name><value>import_pod</value></indexField><indexField><name>pi_level_0</name><value>Akte-Spedition</value></indexField><indexField><name>pi_level_1</name><value>POD</value></indexField><indexField><name>pi_level_2</name><value>Ablieferbeleg</value></indexField><indexField><name>pi_level_3</name><value>2011</value></indexField><indexField><name>pi_mandant_str</name><value>wackler</value></indexField><indexField><name>pi_order_id_str</name><value>201104141300007831012A279ADD09308F0A382E5F11F73AD0E6A00000000ec40eb911f</value></indexField><indexField><name>pi_process_id_str</name><value>201104141300023250a280a56456aac18a8</value></indexField><indexField><name>pi_process_type_str</name><value>POD</value></indexField><indexField><name>pi_sm_status_str</name><value>finished</value></indexField><indexField><name>pi_stack_id_str</name><value>DD-Frachtbr_intern_20110414123806842.split_fileImport_working_20110414125922_814900847_pod</value></indexField></indexFieldList></indexData><additionalProcessInfo/><systemMessages/></process><process><id>201104141300023850a280a56bfe7b4a125</id><documentList><document><id>201104141300021480008D18303023E3AE8850AB4B8B1134CAE9200000000c2bf12be70</id><idType/><actionList/><inputType/><documentType>import_protocol</documentType><indexData><indexFieldList><indexField><name>document_id_str</name><value>201104141300021480008D18303023E3AE8850AB4B8B1134CAE9200000000c2bf12be70</value></indexField><indexField><name>document_type_str</name><value>Ablieferbeleg</value></indexField><indexField><name>dokumentennummer_str</name><value>41122089</value></indexField><indexField><name>export_boolean</name><value>false</value></indexField><indexField><name>input_file_name_str</name><value>/mnt/work/servicemix/working_directory/import/imported/wackler/DD-Frachtbr_intern_20110414123806842.split_fileImport_working_20110414125922_814900847_pod_201104141300037827949/201104141300021480008D18303023E3AE8850AB4B8B1134CAE9200000000c2bf12be70_11851178</value></indexField><indexField><name>page_count_int</name><value>3</value></indexField><indexField><name>recovery_id_ftxt</name><value> OXSEED-8071 OXSEED-8071J</value></indexField><indexField><name>recovery_id_str</name><value>OXSEED-8071A2</value></indexField><indexField><name>toverify_boolean</name><value>false</value></indexField><indexField><name>update_boolean</name><value>false</value></indexField></indexFieldList></indexData><additionalDocumentInfo/></document></documentList><actionList/><processType>administration</processType><processPriority/><indexData><indexFieldList><indexField><name>pi_eingangsdatum_date</name><value>2011-04-14T13:00:02.388Z</value></indexField><indexField><name>pi_full_path</name><value>/Akte-Spedition/POD/Ablieferbeleg/2011/</value></indexField><indexField><name>pi_import_path_str</name><value>/mnt/shared/wackler/import@wackler.oxseed.net/data/pod/ablieferbeleg/intern/201104141240/DD-Frachtbr_intern_20110414123806842.split</value></indexField><indexField><name>pi_inputchannel_str</name><value>import_pod</value></indexField><indexField><name>pi_level_0</name><value>Akte-Spedition</value></indexField><indexField><name>pi_level_1</name><value>POD</value></indexField><indexField><name>pi_level_2</name><value>Ablieferbeleg</value></indexField><indexField><name>pi_level_3</name><value>2011</value></indexField><indexField><name>pi_mandant_str</name><value>wackler</value></indexField><indexField><name>pi_order_id_str</name><value>201104141300007831012A279ADD09308F0A382E5F11F73AD0E6A00000000ec40eb911f</value></indexField><indexField><name>pi_process_id_str</name><value>201104141300023850a280a56bfe7b4a125</value></indexField><indexField><name>pi_process_type_str</name><value>POD</value></indexField><indexField><name>pi_sm_status_str</name><value>finished</value></indexField><indexField><name>pi_stack_id_str</name><value>DD-Frachtbr_intern_20110414123806842.split_fileImport_working_20110414125922_814900847_pod</value></indexField></indexFieldList></indexData><additionalProcessInfo/><systemMessages/></process><process><id>201104141300023790a280a56db500fac9c</id><documentList><document><id>2011041413000204400080DDD5C8C5A80700E6CFC2EC8A02BE364000000002af3c5ecf8</id><idType/><actionList/><inputType/><documentType>import_protocol</documentType><indexData><indexFieldList><indexField><name>document_id_str</name><value>2011041413000204400080DDD5C8C5A80700E6CFC2EC8A02BE364000000002af3c5ecf8</value></indexField><indexField><name>document_type_str</name><value>Ablieferbeleg</value></indexField><indexField><name>dokumentennummer_str</name><value>41122117</value></indexField><indexField><name>export_boolean</name><value>false</value></indexField><indexField><name>input_file_name_str</name><value>/mnt/work/servicemix/working_directory/import/imported/wackler/DD-Frachtbr_intern_20110414123806842.split_fileImport_working_20110414125922_814900847_pod_201104141300037827949/2011041413000204400080DDD5C8C5A80700E6CFC2EC8A02BE364000000002af3c5ecf8_15732879</value></indexField><indexField><name>page_count_int</name><value>1</value></indexField><indexField><name>recovery_id_ftxt</name><value> OXSEED-8071 OXSEED-8071J</value></indexField><indexField><name>recovery_id_str</name><value>OXSEED-8071A2</value></indexField><indexField><name>toverify_boolean</name><value>false</value></indexField><indexField><name>update_boolean</name><value>false</value></indexField></indexFieldList></indexData><additionalDocumentInfo/></document></documentList><actionList/><processType>administration</processType><processPriority/><indexData><indexFieldList><indexField><name>pi_eingangsdatum_date</name><value>2011-04-14T13:00:02.382Z</value></indexField><indexField><name>pi_full_path</name><value>/Akte-Spedition/POD/Ablieferbeleg/2011/</value></indexField><indexField><name>pi_import_path_str</name><value>/mnt/shared/wackler/import@wackler.oxseed.net/data/pod/ablieferbeleg/intern/201104141240/DD-Frachtbr_intern_20110414123806842.split</value></indexField><indexField><name>pi_inputchannel_str</name><value>import_pod</value></indexField><indexField><name>pi_level_0</name><value>Akte-Spedition</value></indexField><indexField><name>pi_level_1</name><value>POD</value></indexField><indexField><name>pi_level_2</name><value>Ablieferbeleg</value></indexField><indexField><name>pi_level_3</name><value>2011</value></indexField><indexField><name>pi_mandant_str</name><value>wackler</value></indexField><indexField><name>pi_order_id_str</name><value>201104141300007831012A279ADD09308F0A382E5F11F73AD0E6A00000000ec40eb911f</value></indexField><indexField><name>pi_process_id_str</name><value>201104141300023790a280a56db500fac9c</value></indexField><indexField><name>pi_process_type_str</name><value>POD</value></indexField><indexField><name>pi_sm_status_str</name><value>finished</value></indexField><indexField><name>pi_stack_id_str</name><value>DD-Frachtbr_intern_20110414123806842.split_fileImport_working_20110414125922_814900847_pod</value></indexField></indexFieldList></indexData><additionalProcessInfo/><systemMessages/></process><process><id>201104141300023760a280a565239669cf1</id><documentList><document><id>2011041413000199100083B9E46B0CF2CD2F71D5E5037024D269B00000000c87a0780ef</id><idType/><actionList/><inputType/><documentType>import_protocol</documentType><indexData><indexFieldList><indexField><name>document_id_str</name><value>2011041413000199100083B9E46B0CF2CD2F71D5E5037024D269B00000000c87a0780ef</value></indexField><indexField><name>document_type_str</name><value>Ablieferbeleg</value></indexField><indexField><name>dokumentennummer_str</name><value>41122123</value></indexField><indexField><name>export_boolean</name><value>false</value></indexField><indexField><name>input_file_name_str</name><value>/mnt/work/servicemix/working_directory/import/imported/wackler/DD-Frachtbr_intern_20110414123806842.split_fileImport_working_20110414125922_814900847_pod_201104141300037827949/2011041413000199100083B9E46B0CF2CD2F71D5E5037024D269B00000000c87a0780ef_13041328</value></indexField><indexField><name>page_count_int</name><value>1</value></indexField><indexField><name>recovery_id_ftxt</name><value> OXSEED-8071 OXSEED-8071J</value></indexField><indexField><name>recovery_id_str</name><value>OXSEED-8071A2</value></indexField><indexField><name>toverify_boolean</name><value>false</value></indexField><indexField><name>update_boolean</name><value>false</value></indexField></indexFieldList></indexData><additionalDocumentInfo/></document></documentList><actionList/><processType>administration</processType><processPriority/><indexData><indexFieldList><indexField><name>pi_eingangsdatum_date</name><value>2011-04-14T13:00:02.379Z</value></indexField><indexField><name>pi_full_path</name><value>/Akte-Spedition/POD/Ablieferbeleg/2011/</value></indexField><indexField><name>pi_import_path_str</name><value>/mnt/shared/wackler/import@wackler.oxseed.net/data/pod/ablieferbeleg/intern/201104141240/DD-Frachtbr_intern_20110414123806842.split</value></indexField><indexField><name>pi_inputchannel_str</name><value>import_pod</value></indexField><indexField><name>pi_level_0</name><value>Akte-Spedition</value></indexField><indexField><name>pi_level_1</name><value>POD</value></indexField><indexField><name>pi_level_2</name><value>Ablieferbeleg</value></indexField><indexField><name>pi_level_3</name><value>2011</value></indexField><indexField><name>pi_mandant_str</name><value>wackler</value></indexField><indexField><name>pi_order_id_str</name><value>201104141300007831012A279ADD09308F0A382E5F11F73AD0E6A00000000ec40eb911f</value></indexField><indexField><name>pi_process_id_str</name><value>201104141300023760a280a565239669cf1</value></indexField><indexField><name>pi_process_type_str</name><value>POD</value></indexField><indexField><name>pi_sm_status_str</name><value>finished</value></indexField><indexField><name>pi_stack_id_str</name><value>DD-Frachtbr_intern_20110414123806842.split_fileImport_working_20110414125922_814900847_pod</value></indexField></indexFieldList></indexData><additionalProcessInfo/><systemMessages/></process><process><id>201104141300023130a280a56678a25e343</id><documentList><document><id>201104141300008980008B413C8CDD989A3A494262456B6B782A300000000009de5ee64</id><idType/><actionList/><inputType/><documentType>import_protocol</documentType><indexData><indexFieldList><indexField><name>document_id_str</name><value>201104141300008980008B413C8CDD989A3A494262456B6B782A300000000009de5ee64</value></indexField><indexField><name>document_type_str</name><value>Ablieferbeleg</value></indexField><indexField><name>dokumentennummer_str</name><value>41122297</value></indexField><indexField><name>export_boolean</name><value>false</value></indexField><indexField><name>input_file_name_str</name><value>/mnt/work/servicemix/working_directory/import/imported/wackler/DD-Frachtbr_intern_20110414123806842.split_fileImport_working_20110414125922_814900847_pod_201104141300037827949/201104141300008980008B413C8CDD989A3A494262456B6B782A300000000009de5ee64_17135752</value></indexField><indexField><name>page_count_int</name><value>1</value></indexField><indexField><name>recovery_id_ftxt</name><value> OXSEED-8071 OXSEED-8071J</value></indexField><indexField><name>recovery_id_str</name><value>OXSEED-8071A2</value></indexField><indexField><name>toverify_boolean</name><value>false</value></indexField><indexField><name>update_boolean</name><value>false</value></indexField></indexFieldList></indexData><additionalDocumentInfo/></document></documentList><actionList/><processType>administration</processType><processPriority/><indexData><indexFieldList><indexField><name>pi_eingangsdatum_date</name><value>2011-04-14T13:00:02.316Z</value></indexField><indexField><name>pi_full_path</name><value>/Akte-Spedition/POD/Ablieferbeleg/2011/</value></indexField><indexField><name>pi_import_path_str</name><value>/mnt/shared/wackler/import@wackler.oxseed.net/data/pod/ablieferbeleg/intern/201104141240/DD-Frachtbr_intern_20110414123806842.split</value></indexField><indexField><name>pi_inputchannel_str</name><value>import_pod</value></indexField><indexField><name>pi_level_0</name><value>Akte-Spedition</value></indexField><indexField><name>pi_level_1</name><value>POD</value></indexField><indexField><name>pi_level_2</name><value>Ablieferbeleg</value></indexField><indexField><name>pi_level_3</name><value>2011</value></indexField><indexField><name>pi_mandant_str</name><value>wackler</value></indexField><indexField><name>pi_order_id_str</name><value>201104141300007831012A279ADD09308F0A382E5F11F73AD0E6A00000000ec40eb911f</value></indexField><indexField><name>pi_process_id_str</name><value>201104141300023130a280a56678a25e343</value></indexField><indexField><name>pi_process_type_str</name><value>POD</value></indexField><indexField><name>pi_sm_status_str</name><value>finished</value></indexField><indexField><name>pi_stack_id_str</name><value>DD-Frachtbr_intern_20110414123806842.split_fileImport_working_20110414125922_814900847_pod</value></indexField></indexFieldList></indexData><additionalProcessInfo/><systemMessages/></process><process><id>201104141300023610a280a5633e99cf595</id><documentList><document><id>2011041413000174100084728768E35713AB8DBBC475E6A387776000000000d25dd721b</id><idType/><actionList/><inputType/><documentType>import_protocol</documentType><indexData><indexFieldList><indexField><name>document_id_str</name><value>2011041413000174100084728768E35713AB8DBBC475E6A387776000000000d25dd721b</value></indexField><indexField><name>document_type_str</name><value>Ablieferbeleg</value></indexField><indexField><name>dokumentennummer_str</name><value>41122118</value></indexField><indexField><name>export_boolean</name><value>false</value></indexField><indexField><name>input_file_name_str</name><value>/mnt/work/servicemix/working_directory/import/imported/wackler/DD-Frachtbr_intern_20110414123806842.split_fileImport_working_20110414125922_814900847_pod_201104141300037827949/2011041413000174100084728768E35713AB8DBBC475E6A387776000000000d25dd721b_14078659</value></indexField><indexField><name>page_count_int</name><value>1</value></indexField><indexField><name>recovery_id_ftxt</name><value> OXSEED-8071 OXSEED-8071J</value></indexField><indexField><name>recovery_id_str</name><value>OXSEED-8071A2</value></indexField><indexField><name>toverify_boolean</name><value>false</value></indexField><indexField><name>update_boolean</name><value>false</value></indexField></indexFieldList></indexData><additionalDocumentInfo/></document></documentList><actionList/><processType>administration</processType><processPriority/><indexData><indexFieldList><indexField><name>pi_eingangsdatum_date</name><value>2011-04-14T13:00:02.364Z</value></indexField><indexField><name>pi_full_path</name><value>/Akte-Spedition/POD/Ablieferbeleg/2011/</value></indexField><indexField><name>pi_import_path_str</name><value>/mnt/shared/wackler/import@wackler.oxseed.net/data/pod/ablieferbeleg/intern/201104141240/DD-Frachtbr_intern_20110414123806842.split</value></indexField><indexField><name>pi_inputchannel_str</name><value>import_pod</value></indexField><indexField><name>pi_level_0</name><value>Akte-Spedition</value></indexField><indexField><name>pi_level_1</name><value>POD</value></indexField><indexField><name>pi_level_2</name><value>Ablieferbeleg</value></indexField><indexField><name>pi_level_3</name><value>2011</value></indexField><indexField><name>pi_mandant_str</name><value>wackler</value></indexField><indexField><name>pi_order_id_str</name><value>201104141300007831012A279ADD09308F0A382E5F11F73AD0E6A00000000ec40eb911f</value></indexField><indexField><name>pi_process_id_str</name><value>201104141300023610a280a5633e99cf595</value></indexField><indexField><name>pi_process_type_str</name><value>POD</value></indexField><indexField><name>pi_sm_status_str</name><value>finished</value></indexField><indexField><name>pi_stack_id_str</name><value>DD-Frachtbr_intern_20110414123806842.split_fileImport_working_20110414125922_814900847_pod</value></indexField></indexFieldList></indexData><additionalProcessInfo/><systemMessages/></process><process><id>201104141300023550a280a56a02a91cc95</id><documentList><document><id>20110414130001640000819C5995B0C99E8E3B01A167686DFF47F00000000d130d44620</id><idType/><actionList/><inputType/><documentType>import_protocol</documentType><indexData><indexFieldList><indexField><name>document_id_str</name><value>20110414130001640000819C5995B0C99E8E3B01A167686DFF47F00000000d130d44620</value></indexField><indexField><name>document_type_str</name><value>Ablieferbeleg</value></indexField><indexField><name>dokumentennummer_str</name><value>41122167</value></indexField><indexField><name>export_boolean</name><value>false</value></indexField><indexField><name>input_file_name_str</name><value>/mnt/work/servicemix/working_directory/import/imported/wackler/DD-Frachtbr_intern_20110414123806842.split_fileImport_working_20110414125922_814900847_pod_201104141300037827949/20110414130001640000819C5995B0C99E8E3B01A167686DFF47F00000000d130d44620_26034872</value></indexField><indexField><name>page_count_int</name><value>1</value></indexField><indexField><name>recovery_id_ftxt</name><value> OXSEED-8071 OXSEED-8071J</value></indexField><indexField><name>recovery_id_str</name><value>OXSEED-8071A2</value></indexField><indexField><name>toverify_boolean</name><value>false</value></indexField><indexField><name>update_boolean</name><value>false</value></indexField></indexFieldList></indexData><additionalDocumentInfo/></document></documentList><actionList/><processType>administration</processType><processPriority/><indexData><indexFieldList><indexField><name>pi_eingangsdatum_date</name><value>2011-04-14T13:00:02.358Z</value></indexField><indexField><name>pi_full_path</name><value>/Akte-Spedition/POD/Ablieferbeleg/2011/</value></indexField><indexField><name>pi_import_path_str</name><value>/mnt/shared/wackler/import@wackler.oxseed.net/data/pod/ablieferbeleg/intern/201104141240/DD-Frachtbr_intern_20110414123806842.split</value></indexField><indexField><name>pi_inputchannel_str</name><value>import_pod</value></indexField><indexField><name>pi_level_0</name><value>Akte-Spedition</value></indexField><indexField><name>pi_level_1</name><value>POD</value></indexField><indexField><name>pi_level_2</name><value>Ablieferbeleg</value></indexField><indexField><name>pi_level_3</name><value>2011</value></indexField><indexField><name>pi_mandant_str</name><value>wackler</value></indexField><indexField><name>pi_order_id_str</name><value>201104141300007831012A279ADD09308F0A382E5F11F73AD0E6A00000000ec40eb911f</value></indexField><indexField><name>pi_process_id_str</name><value>201104141300023550a280a56a02a91cc95</value></indexField><indexField><name>pi_process_type_str</name><value>POD</value></indexField><indexField><name>pi_sm_status_str</name><value>finished</value></indexField><indexField><name>pi_stack_id_str</name><value>DD-Frachtbr_intern_20110414123806842.split_fileImport_working_20110414125922_814900847_pod</value></indexField></indexFieldList></indexData><additionalProcessInfo/><systemMessages/></process></processList><additionalStackInfo/></stack><actionList/><mandant>wackler</mandant><inputChannel/><exportChannel/><additionalOrderInfo/></ns2:order>