<?xml version="1.0" encoding="UTF-8"?><ns2:order xmlns:ns2="http://oxseed.com/data/order" xmlns:ns3="http://oxseed.com/data/commons/entrylist" xmlns:ns4="http://oxseed.com/data/extension/metadata" xmlns:ns5="http://oxseed.com/data/extension/orderdeps"><id>2011041510071844410127C391F543BA4357291DF4F9D826607EC00000000d98236ee41</id><stack><id>DD-Frachtbr_intern_20110415095341735.split_fileImport_working_20110415100716_502119047_pod</id><processList><process><id>201104151007184670a280a5653a872d9b7</id><documentList><document><id></id><idType/><actionList/><inputType/><documentType>import_protocol</documentType><indexData><indexFieldList><indexField><name>document_id_str</name><value>201104151007184520008BD55ACA7C8FE3267636CF1A9C358144C00000000a9b0cb2503</value></indexField><indexField><name>document_type_str</name><value>Ablieferbeleg</value></indexField><indexField><name>dokumentennummer_str</name><value>41123731</value></indexField><indexField><name>export_boolean</name><value>false</value></indexField><indexField><name>input_file_name_str</name><value>/mnt/work/servicemix/working_directory/import/imported/wackler/DD-Frachtbr_intern_20110415095341735.split_fileImport_working_20110415100716_502119047_pod_201104151007190791620/201104151007184520008BD55ACA7C8FE3267636CF1A9C358144C00000000a9b0cb2503_59474465</value></indexField><indexField><name>page_count_int</name><value>1</value></indexField><indexField><name>recovery_id_ftxt</name><value> OXSEED-8071 OXSEED-8071J</value></indexField><indexField><name>recovery_id_str</name><value>OXSEED-8071A2</value></indexField><indexField><name>toverify_boolean</name><value>false</value></indexField><indexField><name>update_boolean</name><value>false</value></indexField></indexFieldList></indexData><additionalDocumentInfo/></document></documentList><actionList/><processType>administration</processType><processPriority/><indexData><indexFieldList><indexField><name>pi_eingangsdatum_date</name><value>2011-04-15T10:07:18.470Z</value></indexField><indexField><name>pi_full_path</name><value>/Akte-Spedition/POD/Ablieferbeleg/2011/</value></indexField><indexField><name>pi_import_path_str</name><value>/mnt/shared/wackler/import@wackler.oxseed.net/data/pod/ablieferbeleg/intern/201104150955/DD-Frachtbr_intern_20110415095341735.split</value></indexField><indexField><name>pi_inputchannel_str</name><value>import_pod</value></indexField><indexField><name>pi_level_0</name><value>Akte-Spedition</value></indexField><indexField><name>pi_level_1</name><value>POD</value></indexField><indexField><name>pi_level_2</name><value>Ablieferbeleg</value></indexField><indexField><name>pi_level_3</name><value>2011</value></indexField><indexField><name>pi_mandant_str</name><value>wackler</value></indexField><indexField><name>pi_order_id_str</name><value>2011041510071844410127C391F543BA4357291DF4F9D826607EC00000000d98236ee41</value></indexField><indexField><name>pi_process_id_str</name><value>201104151007184670a280a5653a872d9b7</value></indexField><indexField><name>pi_process_type_str</name><value>POD</value></indexField><indexField><name>pi_sm_status_str</name><value>finished</value></indexField><indexField><name>pi_stack_id_str</name><value>DD-Frachtbr_intern_20110415095341735.split_fileImport_working_20110415100716_502119047_pod</value></indexField></indexFieldList></indexData><additionalProcessInfo/><systemMessages/></process><process><id>201104151007184700a280a567fb4ae7fbe</id><documentList><document><id></id><idType/><actionList/><inputType/><documentType>import_protocol</documentType><indexData><indexFieldList><indexField><name>document_id_str</name><value>201104151007184650008E818A6DF1DA0CEA497D192536AFCE3A8000000008d199b00a6</value></indexField><indexField><name>document_type_str</name><value>Ablieferbeleg</value></indexField><indexField><name>dokumentennummer_str</name><value>41123778</value></indexField><indexField><name>export_boolean</name><value>false</value></indexField><indexField><name>input_file_name_str</name><value>/mnt/work/servicemix/working_directory/import/imported/wackler/DD-Frachtbr_intern_20110415095341735.split_fileImport_working_20110415100716_502119047_pod_201104151007190791620/201104151007184650008E818A6DF1DA0CEA497D192536AFCE3A8000000008d199b00a6_13630976</value></indexField><indexField><name>page_count_int</name><value>3</value></indexField><indexField><name>recovery_id_ftxt</name><value> OXSEED-8071 OXSEED-8071J</value></indexField><indexField><name>recovery_id_str</name><value>OXSEED-8071A2</value></indexField><indexField><name>toverify_boolean</name><value>false</value></indexField><indexField><name>update_boolean</name><value>false</value></indexField></indexFieldList></indexData><additionalDocumentInfo/></document></documentList><actionList/><processType>administration</processType><processPriority/><indexData><indexFieldList><indexField><name>pi_eingangsdatum_date</name><value>2011-04-15T10:07:18.473Z</value></indexField><indexField><name>pi_full_path</name><value>/Akte-Spedition/POD/Ablieferbeleg/2011/</value></indexField><indexField><name>pi_import_path_str</name><value>/mnt/shared/wackler/import@wackler.oxseed.net/data/pod/ablieferbeleg/intern/201104150955/DD-Frachtbr_intern_20110415095341735.split</value></indexField><indexField><name>pi_inputchannel_str</name><value>import_pod</value></indexField><indexField><name>pi_level_0</name><value>Akte-Spedition</value></indexField><indexField><name>pi_level_1</name><value>POD</value></indexField><indexField><name>pi_level_2</name><value>Ablieferbeleg</value></indexField><indexField><name>pi_level_3</name><value>2011</value></indexField><indexField><name>pi_mandant_str</name><value>wackler</value></indexField><indexField><name>pi_order_id_str</name><value>2011041510071844410127C391F543BA4357291DF4F9D826607EC00000000d98236ee41</value></indexField><indexField><name>pi_process_id_str</name><value>201104151007184700a280a567fb4ae7fbe</value></indexField><indexField><name>pi_process_type_str</name><value>POD</value></indexField><indexField><name>pi_sm_status_str</name><value>finished</value></indexField><indexField><name>pi_stack_id_str</name><value>DD-Frachtbr_intern_20110415095341735.split_fileImport_working_20110415100716_502119047_pod</value></indexField></indexFieldList></indexData><additionalProcessInfo/><systemMessages/></process></processList><additionalStackInfo/></stack><actionList/><mandant>wackler</mandant><inputChannel/><exportChannel/><additionalOrderInfo/></ns2:order>