<?xml version="1.0" encoding="UTF-8"?><ns2:order xmlns:ns2="http://oxseed.com/data/order" xmlns:ns3="http://oxseed.com/data/commons/entrylist" xmlns:ns4="http://oxseed.com/data/extension/metadata" xmlns:ns5="http://oxseed.com/data/extension/orderdeps"><id>201203150113256591012AFFB61AE27BAC65B0B8440311A1C74EA000000006acd9ef20a</id><stack><id>2012031500512819122220186163674</id><processList><process><id>201203150113256690a280a565cd632a22e</id><documentList><document><id>201203150113256680018D41D8CD98F00B204E9800998ECF8427E00000000f741dfd561</id><idType/><actionList/><inputType/><documentType>import_protocol</documentType><indexData><indexFieldList><indexField><name>adressrolle1_str</name><value>Frachtzahler</value></indexField><indexField><name>archivimportquelle_str</name><value>DLE</value></indexField><indexField><name>default_ftxt</name><value>finanzen4814@joebstl.at BSTL GESELLSCHAFT M.B.H.       Bei inner 357171;finanzen4814@joebstl.at;;28.06.2011;01-Wackler;;;2 EBillingProcessFlow file_import_ascii_page72_logo_ebilling 2012-02-29 2012-03-15 Frachtzahler 357171 337,55 wackler_ebilling_de_en 12010637 DLE </value></indexField><indexField><name>document_id_str</name><value>201203150113256680018D41D8CD98F00B204E9800998ECF8427E00000000f741dfd561</value></indexField><indexField><name>document_type_str</name><value>Rechnung</value></indexField><indexField><name>dokumentdatum_date</name><value>2012-02-29T00:00:00.000Z</value></indexField><indexField><name>dokumentennummer_str</name><value>12010637</value></indexField><indexField><name>frachtzahlernummer_str</name><value>357171</value></indexField><indexField><name>gesamtbetrag_brutto_double</name><value>337.55</value></indexField><indexField><name>input_file_name_str</name><value>/mnt/work/servicemix/working_directory/import/imported/wackler/2012031500512819122220186163674_201203150114322864413/201203150051281910008E945A518533E91F107AF231C666127F27F000002B543311641_29972076</value></indexField><indexField><name>mandant_str</name><value>01</value></indexField><indexField><name>name1_ftxt</name><value>BSTL GESELLSCHAFT M.B.H.       Bei inner</value></indexField><indexField><name>page_count_int</name><value>2</value></indexField><indexField><name>versanddatum_date</name><value>2012-03-15T01:25:11.486Z</value></indexField></indexFieldList></indexData><additionalDocumentInfo/></document></documentList><actionList/><processType>administration</processType><processPriority/><indexData><indexFieldList><indexField><name>pi_ebilling_boolean</name><value>true</value></indexField><indexField><name>pi_ebilling_email_receiver_str</name><value>finanzen4814@joebstl.at</value></indexField><indexField><name>pi_ebilling_mail_template_id_str</name><value>wackler_ebilling_de_en</value></indexField><indexField><name>pi_ebilling_note_str</name><value>357171;finanzen4814@joebstl.at;;28.06.2011;01-Wackler;;;2</value></indexField><indexField><name>pi_ebilling_with_voucher_boolean</name><value>false</value></indexField><indexField><name>pi_eingangsdatum_date</name><value>2012-03-15T01:14:32.046Z</value></indexField><indexField><name>pi_flowstatus_str</name><value>finalize</value></indexField><indexField><name>pi_full_path</name><value>/Akte-Fibu/Ausgangsrechnung-Gutschrift/01-Wackler/2012/</value></indexField><indexField><name>pi_import_path_str</name><value>/mnt/shared/wackler/import@wackler.oxseed.net/data/soap/import_ascii_page72_logo_ebilling/2012031500512819122220186163674_201203150051349421553_uploaded</value></indexField><indexField><name>pi_inputchannel_str</name><value>file_import_ascii_page72_logo_ebilling</value></indexField><indexField><name>pi_jbpm_actor_id_str</name><value>archived_ebilling</value></indexField><indexField><name>pi_jbpm_id_long</name><value>253153</value></indexField><indexField><name>pi_jbpm_notification_flow_id_str</name><value>EBillingProcessFlow</value></indexField><indexField><name>pi_level_0</name><value>Akte-Fibu</value></indexField><indexField><name>pi_level_1</name><value>Ausgangsrechnung-Gutschrift</value></indexField><indexField><name>pi_level_2</name><value>01-Wackler</value></indexField><indexField><name>pi_level_3</name><value>2012</value></indexField><indexField><name>pi_mandant_str</name><value>wackler</value></indexField><indexField><name>pi_order_id_str</name><value>201203150113256591012AFFB61AE27BAC65B0B8440311A1C74EA000000006acd9ef20a</value></indexField><indexField><name>pi_process_id_str</name><value>201203150113256690a280a565cd632a22e</value></indexField><indexField><name>pi_process_type_str</name><value>Ausgangsrechnung</value></indexField><indexField><name>pi_sm_status_str</name><value>finished</value></indexField><indexField><name>pi_stack_id_str</name><value>2012031500512819122220186163674</value></indexField><indexField><name>pi_workflow_str</name><value>EBillingProcessFlow_3</value></indexField></indexFieldList></indexData><additionalProcessInfo/><systemMessages/></process></processList><additionalStackInfo/></stack><actionList/><mandant>wackler</mandant><inputChannel/><exportChannel/><additionalOrderInfo/></ns2:order>